<?xml version="1.0" encoding="utf-8"?>
<linkGrp targType="s" toDoc="en/humandocs/PDFs/EPAR/Sustiva/H-249-en1.xml.gz" fromDoc="de/humandocs/PDFs/EPAR/Sustiva/H-249-de1.xml.gz">
	<link certainty="2.55" xtargets="s1.1;s1.1" id="SL2"></link>
	<link certainty="0.3" xtargets="s2.1;s2.1" id="SL4"></link>
	<link certainty="1.46409" xtargets="s3.1;s3.1" id="SL6"></link>
	<link certainty="1.8" xtargets="s4.1;s4.1" id="SL8"></link>
	<link certainty="0.5375" xtargets="s5.1;s5.1" id="SL10"></link>
	<link certainty="1.019152" xtargets="s6.1;s6.1 s6.2" id="SL12"></link>
	<link certainty="1.631263" xtargets="s6.2;s6.3" id="SL13"></link>
	<link certainty="0.76197" xtargets="s6.3;s6.4" id="SL14"></link>
	<link certainty="2.294915" xtargets="s7.1;s7.1" id="SL16"></link>
	<link certainty="1.594915" xtargets="s7.2;s7.2" id="SL17"></link>
	<link certainty="8.1" xtargets="s7.3;s7.3" id="SL18"></link>
	<link certainty="14.55" xtargets="s7.4;s7.4" id="SL19"></link>
	<link certainty="10.10203" xtargets="s7.5;s7.5" id="SL20"></link>
	<link certainty="2.85203" xtargets="s7.6;s7.6" id="SL21"></link>
	<link certainty="2.051693" xtargets="s8.1;s8.1" id="SL23"></link>
	<link certainty="2.641653" xtargets="s8.2;s8.2" id="SL24"></link>
	<link certainty="2.611531" xtargets="s8.3;s8.3" id="SL25"></link>
	<link certainty="0.817021" xtargets="s8.4;s8.4" id="SL26"></link>
	<link certainty="2.007329" xtargets="s9.1;s9.1" id="SL28"></link>
	<link certainty="2.075659" xtargets="s9.2;s9.2" id="SL29"></link>
	<link certainty="1.782059" xtargets="s9.3;s9.3" id="SL30"></link>
	<link certainty="4.012149" xtargets="s9.4;s9.4" id="SL31"></link>
	<link certainty="6.27562" xtargets="s9.5;s9.5" id="SL32"></link>
	<link certainty="3.584245" xtargets="s9.6;s9.6" id="SL33"></link>
	<link certainty="1.497706" xtargets="s9.7;s9.7" id="SL34"></link>
	<link certainty="1.805311" xtargets="s9.8;s9.8" id="SL35"></link>
	<link certainty="1.937028" xtargets="s9.9;s9.9" id="SL36"></link>
	<link certainty="1.614684" xtargets="s9.10;s9.10" id="SL37"></link>
	<link certainty="0.758976" xtargets="s9.11;s9.11" id="SL38"></link>
	<link certainty="2.9759" xtargets="s10.1;s10.1" id="SL40"></link>
	<link certainty="1.22884" xtargets="s10.2;s10.2" id="SL41"></link>
	<link certainty="-0.070518" xtargets="s10.3;s10.3 s10.4" id="SL42"></link>
	<link certainty="-0.6" xtargets="s10.4;s10.5" id="SL43"></link>
	<link certainty="8.72143" xtargets="s11.1;s11.1" id="SL45"></link>
	<link certainty="4.35" xtargets="s11.2;s11.2" id="SL46"></link>
	<link certainty="2.887974" xtargets="s12.1;s12.1" id="SL48"></link>
	<link certainty="0.573684" xtargets="s12.2 s12.3;s12.2" id="SL49"></link>
	<link certainty="1.954919" xtargets="s12.4 s13.1;s12.3" id="SL50"></link>
	<link certainty="3.133519" xtargets="s13.2;s12.4" id="SL51"></link>
	<link certainty="2.715086" xtargets="s13.3;s12.5" id="SL52"></link>
	<link certainty="0.548026" xtargets="s13.4 s13.5;s12.6" id="SL53"></link>
	<link certainty="1.001933" xtargets="s14.1;s13.1" id="SL55"></link>
	<link certainty="1.00279" xtargets="s14.2 s14.3 s14.4 s14.5;s13.2" id="SL56"></link>
	<link certainty="1.650857" xtargets="s14.6;s13.3" id="SL57"></link>
	<link certainty="0.770455" xtargets="s14.7;s13.4" id="SL58"></link>
	<link certainty="4.78885" xtargets="s15.1;s14.1" id="SL60"></link>
	<link certainty="4.248349" xtargets="s15.2;s14.2" id="SL61"></link>
	<link certainty="1.773356" xtargets="s15.3;s14.3" id="SL62"></link>
	<link certainty="1.755069" xtargets="s15.4;s14.4" id="SL63"></link>
	<link certainty="1.913462" xtargets="s15.5;s14.5" id="SL64"></link>
	<link certainty="2.31404" xtargets="s15.6;s14.6" id="SL65"></link>
	<link certainty="1.25846" xtargets="s15.7;s14.7" id="SL66"></link>
	<link certainty="0.846294" xtargets="s16.1 s16.2;s14.8" id="SL67"></link>
	<link certainty="1.411549" xtargets="s16.3;s14.9" id="SL68"></link>
	<link certainty="1.717428" xtargets="s16.4;s14.10" id="SL69"></link>
	<link certainty="0.785366" xtargets="s16.5;s14.11" id="SL70"></link>
	<link certainty="2.28339" xtargets="s17.1;s15.1" id="SL72"></link>
	<link certainty="2.9331" xtargets="s17.2;s15.2" id="SL73"></link>
	<link certainty="2.607601" xtargets="s17.3;s15.3" id="SL74"></link>
	<link certainty="1.994521" xtargets="s17.4;s15.4" id="SL75"></link>
	<link certainty="1.32629" xtargets="s17.5;s15.5" id="SL76"></link>
	<link certainty="2.91" xtargets="s18.1;s16.1" id="SL78"></link>
	<link certainty="3.44105" xtargets="s18.2 s18.3;s16.2" id="SL79"></link>
	<link certainty="2.088631" xtargets="s18.4;s16.3" id="SL80"></link>
	<link certainty="-0.002419" xtargets="s18.5 s18.6;s16.4" id="SL81"></link>
	<link certainty="0.92064" xtargets="s18.7;" id="SL82"></link>
	<link certainty="1.22064" xtargets="s19.1;s17.1" id="SL83"></link>
	<link certainty="0.808333" xtargets="s20.1;s18.1" id="SL85"></link>
	<link certainty="0.6" xtargets="s21.1;s19.1" id="SL87"></link>
</linkGrp>