<?xml version="1.0" encoding="utf-8"?>
<linkGrp targType="s" toDoc="en/vetdocs/PDFs/EPAR/gonazon/V-075-en1.xml.gz" fromDoc="de/vetdocs/PDFs/EPAR/gonazon/V-075-de1.xml.gz">
	<link certainty="2.8" xtargets="s1.1;s1.1" id="SL2"></link>
	<link certainty="0.3" xtargets="s2.1;s2.1" id="SL4"></link>
	<link certainty="1.46409" xtargets="s3.1;s3.1" id="SL6"></link>
	<link certainty="1.8" xtargets="s4.1;s4.1" id="SL8"></link>
	<link certainty="1.0375" xtargets="s5.1;s5.1" id="SL10"></link>
	<link certainty="0.735309" xtargets="s6.1;s6.1 s6.2" id="SL12"></link>
	<link certainty="0.898839" xtargets="s6.2;s6.3" id="SL13"></link>
	<link certainty="1.278868" xtargets="s6.3;s6.4" id="SL14"></link>
	<link certainty="0.925743" xtargets="s6.4;s6.5" id="SL15"></link>
	<link certainty="2.61714" xtargets="s7.1;s7.1" id="SL17"></link>
	<link certainty="2.104413" xtargets="s7.2;s7.2" id="SL18"></link>
	<link certainty="1.618011" xtargets="s7.3;s7.3" id="SL19"></link>
	<link certainty="0.630738" xtargets="s7.4;s7.4" id="SL20"></link>
	<link certainty="2.465136" xtargets="s8.1;s8.1" id="SL22"></link>
	<link certainty="1.481591" xtargets="s8.2;s8.2" id="SL23"></link>
	<link certainty="4.831005" xtargets="s8.3;s8.3" id="SL24"></link>
	<link certainty="4.11" xtargets="s8.4;s8.4" id="SL25"></link>
	<link certainty="1.644865" xtargets="s9.1;s9.1" id="SL27"></link>
	<link certainty="1.973334" xtargets="s9.2;s9.2" id="SL28"></link>
	<link certainty="0.991196" xtargets="s9.3;s9.3" id="SL29"></link>
	<link certainty="2.679" xtargets="s10.1;s10.1" id="SL31"></link>
	<link certainty="2.034079" xtargets="s10.2;s10.2" id="SL32"></link>
	<link certainty="0.802139" xtargets="s10.3;s10.3" id="SL33"></link>
	<link certainty="0.539915" xtargets="s11.1;s11.1" id="SL35"></link>
	<link certainty="3.77143" xtargets=";s12.1 s12.2 s12.3" id="SL36"></link>
	<link certainty="7.60007" xtargets="s12.1;s13.1" id="SL37"></link>
	<link certainty="3.77242" xtargets="s12.2;s13.2" id="SL38"></link>
	<link certainty="1.127151" xtargets="s12.3;s13.3" id="SL39"></link>
	<link certainty="0.583371" xtargets="s12.4;s13.4" id="SL40"></link>
	<link certainty="0.214286" xtargets="s13.1 s13.2;s13.5" id="SL41"></link>
	<link certainty="0.279545" xtargets="s13.3 s13.4;" id="SL42"></link>
	<link certainty="1.70229" xtargets="s14.1;s14.1" id="SL43"></link>
	<link certainty="1.648745" xtargets="s14.2;s14.2" id="SL44"></link>
	<link certainty="1.295279" xtargets="s14.3;s14.3" id="SL45"></link>
	<link certainty="1.129279" xtargets="s14.4;s14.4" id="SL46"></link>
	<link certainty="0.66" xtargets="s14.5;s14.5" id="SL47"></link>
	<link certainty="1.63222" xtargets="s15.1;s15.1" id="SL49"></link>
	<link certainty="2.19643" xtargets="s16.1;s16.1" id="SL51"></link>
	<link certainty="1.806705" xtargets="s16.2;s16.2" id="SL52"></link>
	<link certainty="0.651945" xtargets="s16.3;s16.3" id="SL53"></link>
	<link certainty="0.811905" xtargets="s17.1;s17.1" id="SL55"></link>
	<link certainty="0.960836" xtargets="s18.1;s18.1" id="SL57"></link>
	<link certainty="0.337895" xtargets="s18.2;s18.2" id="SL58"></link>
	<link certainty="1.472906" xtargets="s19.1;s19.1" id="SL60"></link>
	<link certainty="1.345283" xtargets="s19.2;s19.2" id="SL61"></link>
	<link certainty="1.244869" xtargets="s19.3;s19.3" id="SL62"></link>
	<link certainty="0.484492" xtargets="s19.4;s19.4" id="SL63"></link>
	<link certainty="2.258861" xtargets="s20.1;s20.1" id="SL65"></link>
	<link certainty="1.578853" xtargets="s20.2;s20.2" id="SL66"></link>
	<link certainty="1.536348" xtargets="s20.3;s20.3" id="SL67"></link>
	<link certainty="4.733086" xtargets="s20.4;s20.4" id="SL68"></link>
	<link certainty="3.79451" xtargets="s20.5;s20.5" id="SL69"></link>
	<link certainty="1.26" xtargets="s21.1;s21.1" id="SL71"></link>
	<link certainty="0.841667" xtargets="s22.1 s23.1 s24.1 s24.2;s21.2" id="SL72"></link>
	<link certainty="0.952231" xtargets="s24.3;s21.3" id="SL73"></link>
	<link certainty="0.485564" xtargets="s24.4;s21.4" id="SL74"></link>
	<link certainty="0.160976" xtargets="s25.1;s22.1" id="SL76"></link>
	<link certainty="12.3" xtargets="s26.1;s23.1" id="SL78"></link>
	<link certainty="0.6" xtargets="s27.1;s24.1" id="SL80"></link>
</linkGrp><?xml version="1.0" encoding="utf-8"?>
<linkGrp targType="s" toDoc="en/vetdocs/PDFs/EPAR/gonazon/V-075-en1.xml.gz" fromDoc="de/vetdocs/PDFs/EPAR/gonazon/V-075-de1.xml.gz">
	<link certainty="2.8" xtargets="s1.1;s1.1" id="SL2"></link>
	<link certainty="0.3" xtargets="s2.1;s2.1" id="SL4"></link>
	<link certainty="1.46409" xtargets="s3.1;s3.1" id="SL6"></link>
	<link certainty="1.8" xtargets="s4.1;s4.1" id="SL8"></link>
	<link certainty="1.0375" xtargets="s5.1;s5.1" id="SL10"></link>
	<link certainty="0.735309" xtargets="s6.1;s6.1 s6.2" id="SL12"></link>
	<link certainty="0.898839" xtargets="s6.2;s6.3" id="SL13"></link>
	<link certainty="1.278868" xtargets="s6.3;s6.4" id="SL14"></link>
	<link certainty="0.925743" xtargets="s6.4;s6.5" id="SL15"></link>
	<link certainty="2.61714" xtargets="s7.1;s7.1" id="SL17"></link>
	<link certainty="2.104413" xtargets="s7.2;s7.2" id="SL18"></link>
	<link certainty="1.618011" xtargets="s7.3;s7.3" id="SL19"></link>
	<link certainty="0.630738" xtargets="s7.4;s7.4" id="SL20"></link>
	<link certainty="2.465136" xtargets="s8.1;s8.1" id="SL22"></link>
	<link certainty="1.481591" xtargets="s8.2;s8.2" id="SL23"></link>
	<link certainty="4.831005" xtargets="s8.3;s8.3" id="SL24"></link>
	<link certainty="4.11" xtargets="s8.4;s8.4" id="SL25"></link>
	<link certainty="1.644865" xtargets="s9.1;s9.1" id="SL27"></link>
	<link certainty="1.973334" xtargets="s9.2;s9.2" id="SL28"></link>
	<link certainty="0.991196" xtargets="s9.3;s9.3" id="SL29"></link>
	<link certainty="2.679" xtargets="s10.1;s10.1" id="SL31"></link>
	<link certainty="2.034079" xtargets="s10.2;s10.2" id="SL32"></link>
	<link certainty="0.802139" xtargets="s10.3;s10.3" id="SL33"></link>
	<link certainty="0.539915" xtargets="s11.1;s11.1" id="SL35"></link>
	<link certainty="3.77143" xtargets=";s12.1 s12.2 s12.3" id="SL36"></link>
	<link certainty="7.60007" xtargets="s12.1;s13.1" id="SL37"></link>
	<link certainty="3.77242" xtargets="s12.2;s13.2" id="SL38"></link>
	<link certainty="1.127151" xtargets="s12.3;s13.3" id="SL39"></link>
	<link certainty="0.583371" xtargets="s12.4;s13.4" id="SL40"></link>
	<link certainty="0.214286" xtargets="s13.1 s13.2;s13.5" id="SL41"></link>
	<link certainty="0.279545" xtargets="s13.3 s13.4;" id="SL42"></link>
	<link certainty="1.70229" xtargets="s14.1;s14.1" id="SL43"></link>
	<link certainty="1.648745" xtargets="s14.2;s14.2" id="SL44"></link>
	<link certainty="1.295279" xtargets="s14.3;s14.3" id="SL45"></link>
	<link certainty="1.129279" xtargets="s14.4;s14.4" id="SL46"></link>
	<link certainty="0.66" xtargets="s14.5;s14.5" id="SL47"></link>
	<link certainty="1.63222" xtargets="s15.1;s15.1" id="SL49"></link>
	<link certainty="2.19643" xtargets="s16.1;s16.1" id="SL51"></link>
	<link certainty="1.806705" xtargets="s16.2;s16.2" id="SL52"></link>
	<link certainty="0.651945" xtargets="s16.3;s16.3" id="SL53"></link>
	<link certainty="0.811905" xtargets="s17.1;s17.1" id="SL55"></link>
	<link certainty="0.960836" xtargets="s18.1;s18.1" id="SL57"></link>
	<link certainty="0.337895" xtargets="s18.2;s18.2" id="SL58"></link>
	<link certainty="1.472906" xtargets="s19.1;s19.1" id="SL60"></link>
	<link certainty="1.345283" xtargets="s19.2;s19.2" id="SL61"></link>
	<link certainty="1.244869" xtargets="s19.3;s19.3" id="SL62"></link>
	<link certainty="0.484492" xtargets="s19.4;s19.4" id="SL63"></link>
	<link certainty="2.258861" xtargets="s20.1;s20.1" id="SL65"></link>
	<link certainty="1.578853" xtargets="s20.2;s20.2" id="SL66"></link>
	<link certainty="1.536348" xtargets="s20.3;s20.3" id="SL67"></link>
	<link certainty="4.733086" xtargets="s20.4;s20.4" id="SL68"></link>
	<link certainty="3.79451" xtargets="s20.5;s20.5" id="SL69"></link>
	<link certainty="1.26" xtargets="s21.1;s21.1" id="SL71"></link>
	<link certainty="0.841667" xtargets="s22.1 s23.1 s24.1 s24.2;s21.2" id="SL72"></link>
	<link certainty="0.952231" xtargets="s24.3;s21.3" id="SL73"></link>
	<link certainty="0.485564" xtargets="s24.4;s21.4" id="SL74"></link>
	<link certainty="0.160976" xtargets="s25.1;s22.1" id="SL76"></link>
	<link certainty="12.3" xtargets="s26.1;s23.1" id="SL78"></link>
	<link certainty="0.6" xtargets="s27.1;s24.1" id="SL80"></link>
</linkGrp>