<?xml version="1.0" encoding="utf-8"?>
<linkGrp targType="s" toDoc="en/humandocs/PDFs/EPAR/competact/H-655-PI-en.xml.gz" fromDoc="de/humandocs/PDFs/EPAR/competact/H-655-PI-de.xml.gz">
	<link certainty="1.25714" xtargets="s1.1;s1.1" id="SL2"></link>
	<link certainty="0.796875" xtargets="s2.1;s2.1" id="SL4"></link>
	<link certainty="13.32692" xtargets="s3.1;s3.1" id="SL6"></link>
	<link certainty="1.02692" xtargets="s3.2;s3.2" id="SL7"></link>
	<link certainty="1.5416" xtargets="s4.1;s4.1" id="SL9"></link>
	<link certainty="3.26842" xtargets="s5.1;s5.1" id="SL11"></link>
	<link certainty="1.46842" xtargets="s5.2;s5.2" id="SL12"></link>
	<link certainty="3.66054" xtargets="s6.1;s6.1" id="SL14"></link>
	<link certainty="0.900682" xtargets="s7.1;s7.1" id="SL16"></link>
	<link certainty="2.064706" xtargets="s8.1;s8.1" id="SL18"></link>
	<link certainty="0.264706" xtargets="s8.2;s8.2" id="SL19"></link>
	<link certainty="0.184615" xtargets="s9.1;s9.1" id="SL21"></link>
	<link certainty="2.58412" xtargets="s10.1;s10.1" id="SL23"></link>
	<link certainty="2.047059" xtargets="s11.1;s11.1" id="SL25"></link>
	<link certainty="0.247059" xtargets="s11.2;s11.2" id="SL26"></link>
	<link certainty="1.22857" xtargets="s12.1;s12.1" id="SL28"></link>
	<link certainty="1.95736" xtargets="s13.1;s13.1" id="SL30"></link>
	<link certainty="0.728571" xtargets="s14.1;s14.1" id="SL32"></link>
	<link certainty="1.16124" xtargets=";s15.1" id="SL33"></link>
	<link certainty="1.46124" xtargets="s15.1;s16.1" id="SL34"></link>
	<link certainty="0.8825" xtargets="s16.1;s17.1" id="SL36"></link>
	<link certainty="0.993333" xtargets="s17.1;s18.1" id="SL38"></link>
	<link certainty="1.70426" xtargets="s18.1;s19.1" id="SL40"></link>
	<link certainty="0.688704" xtargets=";s20.1" id="SL41"></link>
	<link certainty="0.988704" xtargets="s19.1;s21.1" id="SL42"></link>
	<link certainty="2.25018" xtargets=";s22.1" id="SL43"></link>
	<link certainty="2.55018" xtargets="s20.1;s23.1" id="SL44"></link>
	<link certainty="1.00493" xtargets=";s24.1" id="SL45"></link>
	<link certainty="1.30493" xtargets="s21.1;s25.1" id="SL46"></link>
	<link certainty="0.7648" xtargets=";s26.1" id="SL47"></link>
	<link certainty="1.0648" xtargets="s22.1;s27.1" id="SL48"></link>
	<link certainty="1.22941" xtargets="s23.1;s28.1" id="SL50"></link>
	<link certainty="1.03571" xtargets="s24.1;s29.1" id="SL52"></link>
	<link certainty="0.786438" xtargets="s25.1;s30.1" id="SL54"></link>
	<link certainty="1.88464" xtargets="s26.1;s31.1" id="SL56"></link>
	<link certainty="0.83791" xtargets="s27.1;" id="SL57"></link>
	<link certainty="1.13791" xtargets="s28.1;s32.1" id="SL58"></link>
	<link certainty="-0.136364" xtargets="s29.1;s33.1" id="SL60"></link>
	<link certainty="1.18947" xtargets="s30.1;s34.1" id="SL62"></link>
	<link certainty="0.775676" xtargets="s31.1;s35.1" id="SL64"></link>
	<link certainty="1.08964" xtargets="s32.1;s36.1" id="SL66"></link>
	<link certainty="4.20385" xtargets="s33.1;s37.1" id="SL68"></link>
	<link certainty="0.652308" xtargets="s34.1;" id="SL69"></link>
	<link certainty="0.952308" xtargets="s35.1;s38.1" id="SL70"></link>
	<link certainty="1.25385" xtargets="s36.1;s39.1" id="SL72"></link>
	<link certainty="0.997059" xtargets="s37.1;s40.1" id="SL74"></link>
	<link certainty="1.25714" xtargets="s38.1;s41.1" id="SL76"></link>
	<link certainty="1.37245" xtargets="s39.1;s42.1" id="SL78"></link>
	<link certainty="1.3" xtargets="s40.1;s43.1" id="SL80"></link>
	<link certainty="1.24038" xtargets="s41.1;s44.1" id="SL82"></link>
	<link certainty="1.13397" xtargets="s42.1;s45.1" id="SL84"></link>
	<link certainty="0.312245" xtargets=";s46.1" id="SL85"></link>
	<link certainty="1.451864" xtargets="s43.1;s47.1" id="SL86"></link>
	<link certainty="1.507397" xtargets="s43.2;s47.2" id="SL87"></link>
	<link certainty="0.667778" xtargets="s43.3;s47.3" id="SL88"></link>
	<link certainty="0.09735" xtargets=";s48.1" id="SL89"></link>
	<link certainty="1.036128" xtargets="s44.1;s49.1" id="SL90"></link>
	<link certainty="1.684298" xtargets="s44.2;s49.2" id="SL91"></link>
	<link certainty="1.04552" xtargets="s44.3;s49.3" id="SL92"></link>
	<link certainty="0.051196" xtargets=";s50.1" id="SL93"></link>
	<link certainty="0.351196" xtargets="s45.1;s51.1" id="SL94"></link>
	<link certainty="1.12353" xtargets="s46.1;s52.1" id="SL96"></link>
	<link certainty="0.728571" xtargets="s47.1;s53.1" id="SL98"></link>
	<link certainty="0.444444" xtargets="s48.1;s54.1" id="SL100"></link>
	<link certainty="0.955943" xtargets="s49.1;s55.1" id="SL102"></link>
	<link certainty="0.223107" xtargets="s49.2 s49.3;s55.2" id="SL103"></link>
	<link certainty="0.44375" xtargets=";s56.1" id="SL104"></link>
	<link certainty="1.521804" xtargets="s50.1;s57.1" id="SL105"></link>
	<link certainty="1.743054" xtargets="s50.2;s57.2" id="SL106"></link>
	<link certainty="2.18318" xtargets="s50.3;s57.3" id="SL107"></link>
	<link certainty="2.49337" xtargets="s50.4;s57.4" id="SL108"></link>
	<link certainty="2.38902" xtargets="s50.5;s57.5" id="SL109"></link>
	<link certainty="1.11383" xtargets="s50.6;s57.6" id="SL110"></link>
	<link certainty="3.128577" xtargets="s51.1;s58.1" id="SL112"></link>
	<link certainty="1.5646" xtargets="s51.2;s58.2" id="SL113"></link>
	<link certainty="3.688213" xtargets="s51.3;s58.3" id="SL114"></link>
	<link certainty="2.76383" xtargets="s51.4;s58.4" id="SL115"></link>
	<link certainty="0.636842" xtargets=";s59.1" id="SL116"></link>
	<link certainty="1.965712" xtargets="s52.1;s60.1" id="SL117"></link>
	<link certainty="2.07887" xtargets="s52.2;s60.2" id="SL118"></link>
	<link certainty="2.20714" xtargets="s52.3;s60.3" id="SL119"></link>
	<link certainty="1.15714" xtargets="s52.4;s60.4" id="SL120"></link>
	<link certainty="1.572885" xtargets="s53.1;s61.1" id="SL122"></link>
	<link certainty="1.43791" xtargets="s53.2;s61.2" id="SL123"></link>
	<link certainty="1.169698" xtargets="s53.3;s61.3" id="SL124"></link>
	<link certainty="1.259158" xtargets="s53.4;s61.4" id="SL125"></link>
	<link certainty="1.546268" xtargets="s53.5;s61.5" id="SL126"></link>
	<link certainty="0.766667" xtargets="s53.6;s61.6" id="SL127"></link>
	<link certainty="0.536008" xtargets=";s62.1" id="SL128"></link>
	<link certainty="1.664133" xtargets="s54.1;s63.1" id="SL129"></link>
	<link certainty="0.828125" xtargets="s54.2;s63.2" id="SL130"></link>
	<link certainty="1.98607" xtargets=";s64.1" id="SL131"></link>
	<link certainty="3.199204" xtargets="s55.1;s65.1" id="SL132"></link>
	<link certainty="0.913134" xtargets="s55.2;s65.2" id="SL133"></link>
	<link certainty="2.24" xtargets=";s66.1" id="SL134"></link>
	<link certainty="2.54" xtargets="s56.1;s67.1" id="SL135"></link>
	<link certainty="1.113602" xtargets="s57.1;s68.1" id="SL137"></link>
	<link certainty="0.736262" xtargets="s57.2;s68.2" id="SL138"></link>
	<link certainty="0.556262" xtargets="s57.3;s68.3" id="SL139"></link>
	<link certainty="1.61879" xtargets=";s69.1" id="SL140"></link>
	<link certainty="1.91879" xtargets="s58.1;s70.1" id="SL141"></link>
	<link certainty="0.374866" xtargets=";s71.1" id="SL142"></link>
	<link certainty="2.402046" xtargets="s59.1;s72.1" id="SL143"></link>
	<link certainty="1.72718" xtargets="s59.2;s72.2" id="SL144"></link>
	<link certainty="0.552926" xtargets=";s73.1" id="SL145"></link>
	<link certainty="1.225899" xtargets="s60.1;s74.1" id="SL146"></link>
	<link certainty="1.406323" xtargets="s60.2;s74.2" id="SL147"></link>
	<link certainty="1.03335" xtargets="s60.3;s74.3" id="SL148"></link>
	<link certainty="0.73964" xtargets=";s75.1" id="SL149"></link>
	<link certainty="1.03964" xtargets="s61.1;s76.1" id="SL150"></link>
	<link certainty="2.265416" xtargets="s62.1;s77.1" id="SL152"></link>
	<link certainty="1.41968" xtargets="s62.2;s77.2" id="SL153"></link>
	<link certainty="4.15763" xtargets="s63.1;s78.1" id="SL155"></link>
	<link certainty="2.19213" xtargets="s63.2;s78.2" id="SL156"></link>
	<link certainty="1.63414" xtargets="s64.1;s79.1" id="SL158"></link>
	<link certainty="0.55984" xtargets="s64.2;s79.2 s79.3" id="SL159"></link>
	<link certainty="5.22" xtargets=";s80.1 s81.1 s81.2" id="SL160"></link>
	<link certainty="6.12" xtargets="s65.1;s82.1" id="SL161"></link>
	<link certainty="-0.0275099999999999" xtargets="s66.1 s66.2 s66.3 s66.4 s66.5 s66.6 s66.7;s82.2" id="SL162"></link>
	<link certainty="0.953234" xtargets="s67.1;s83.1" id="SL164"></link>
	<link certainty="1.885953" xtargets="s68.1;s84.1" id="SL166"></link>
	<link certainty="0.759533" xtargets="s68.2;s84.2" id="SL167"></link>
	<link certainty="2.05007" xtargets="s69.1;s85.1" id="SL169"></link>
	<link certainty="1.589368" xtargets="s69.2;s85.2" id="SL170"></link>
	<link certainty="1.08736" xtargets="s69.3;s85.3" id="SL171"></link>
	<link certainty="0.507032" xtargets="s69.4;s85.4" id="SL172"></link>
	<link certainty="1.984488" xtargets="s70.1;s86.1" id="SL174"></link>
	<link certainty="2.363198" xtargets="s70.2;s86.2" id="SL175"></link>
	<link certainty="3.86863" xtargets="s70.3;s86.3" id="SL176"></link>
	<link certainty="3.133236" xtargets="s70.4;s86.4" id="SL177"></link>
	<link certainty="2.119366" xtargets="s70.5;s86.5" id="SL178"></link>
	<link certainty="1.42738" xtargets="s70.6;s86.6" id="SL179"></link>
	<link certainty="1.57302" xtargets="s71.1;s87.1" id="SL181"></link>
	<link certainty="0.3" xtargets="s71.2;s87.2" id="SL182"></link>
	<link certainty="2.61601" xtargets="s72.1;s88.1" id="SL184"></link>
	<link certainty="1.59319" xtargets="s72.2;s88.2" id="SL185"></link>
	<link certainty="2.625071" xtargets="s73.1 s73.2;s89.1" id="SL187"></link>
	<link certainty="3.193765" xtargets="s73.3;s89.2" id="SL188"></link>
	<link certainty="0.771905" xtargets="s73.4;s89.3" id="SL189"></link>
	<link certainty="1.252554" xtargets="s74.1;s90.1" id="SL191"></link>
	<link certainty="1.620445" xtargets="s74.2;s90.2" id="SL192"></link>
	<link certainty="0.876761" xtargets="s74.3;s90.3" id="SL193"></link>
	<link certainty="1.108696" xtargets="s75.1;s91.1" id="SL195"></link>
	<link certainty="0.821739" xtargets="s75.2;s91.2" id="SL196"></link>
	<link certainty="0.828" xtargets="s76.1;s92.1" id="SL198"></link>
	<link certainty="0.946429" xtargets="s77.1;s93.1" id="SL200"></link>
	<link certainty="0.363971" xtargets=";s94.1" id="SL201"></link>
	<link certainty="1.481662" xtargets="s78.1;s95.1" id="SL202"></link>
	<link certainty="0.817691" xtargets="s78.2;s95.2" id="SL203"></link>
	<link certainty="0.385417" xtargets=";s96.1" id="SL204"></link>
	<link certainty="1.395527" xtargets="s79.1;s97.1" id="SL205"></link>
	<link certainty="0.71011" xtargets="s79.2;s97.2" id="SL206"></link>
	<link certainty="2.065397" xtargets="s80.1;s98.1" id="SL208"></link>
	<link certainty="1.17564" xtargets="s80.2;s98.2" id="SL209"></link>
	<link certainty="1.442324" xtargets="s81.1;s99.1" id="SL211"></link>
	<link certainty="1.723694" xtargets="s81.2;s99.2" id="SL212"></link>
	<link certainty="1.43467" xtargets="s81.3;s99.3" id="SL213"></link>
	<link certainty="0.307317" xtargets="s82.1;s100.1" id="SL215"></link>
	<link certainty="0.711278" xtargets="s83.1;s101.1" id="SL217"></link>
	<link certainty="2.23333" xtargets="s84.1;s102.1" id="SL219"></link>
	<link certainty="1.37167" xtargets="s85.1;s103.1" id="SL221"></link>
	<link certainty="2.33129" xtargets="s86.1;s104.1" id="SL223"></link>
	<link certainty="2.34596" xtargets="s86.2;s104.2" id="SL224"></link>
	<link certainty="1.04333" xtargets="s86.3;s104.3" id="SL225"></link>
	<link certainty="1.12453" xtargets="s87.1;s105.1" id="SL227"></link>
	<link certainty="0.663636" xtargets="s88.1;s106.1" id="SL229"></link>
	<link certainty="-2.4" xtargets=";s107.1 s108.1 s109.1 s110.1 s111.1 s112.1 s113.1 s114.1 s115.1" id="SL230"></link>
	<link certainty="0.3" xtargets="s89.1;s116.1" id="SL231"></link>
	<link certainty="0.473077" xtargets=";s117.1" id="SL232"></link>
	<link certainty="0.773077" xtargets="s90.1;s118.1" id="SL233"></link>
	<link certainty="-0.081818" xtargets=";s119.1" id="SL234"></link>
	<link certainty="0.218182" xtargets="s91.1;s120.1" id="SL235"></link>
	<link certainty="9.3" xtargets="s92.1;s121.1" id="SL237"></link>
	<link certainty="-0.09" xtargets="s93.1;s122.1" id="SL239"></link>
	<link certainty="0.0375" xtargets="s94.1;s123.1" id="SL241"></link>
	<link certainty="0.3" xtargets="s95.1;s124.1" id="SL243"></link>
	<link certainty="0.13125" xtargets="s96.1;s125.1" id="SL245"></link>
	<link certainty="-0.1125" xtargets="s97.1;" id="SL246"></link>
	<link certainty="0.1875" xtargets="s98.1;s126.1" id="SL247"></link>
	<link certainty="-0.081818" xtargets="s99.1;" id="SL248"></link>
	<link certainty="0.218182" xtargets="s100.1;s127.1" id="SL249"></link>
	<link certainty="1.22105" xtargets="s101.1;s128.1" id="SL251"></link>
	<link certainty="0.157895" xtargets="s102.1;s129.1" id="SL253"></link>
	<link certainty="-0.6" xtargets="s103.1;s130.1" id="SL255"></link>
	<link certainty="0.3" xtargets="s104.1;s131.1" id="SL257"></link>
	<link certainty="1.659754" xtargets="s105.1;s132.1" id="SL259"></link>
	<link certainty="0.568914" xtargets="s105.2;s132.2" id="SL260"></link>
	<link certainty="1.900589" xtargets="s106.1;s133.1" id="SL262"></link>
	<link certainty="0.933158" xtargets="s106.2;s133.2" id="SL263"></link>
	<link certainty="0.264935" xtargets="s107.1 s107.2;s134.1" id="SL265"></link>
	<link certainty="1.824008" xtargets="s108.1;s135.1" id="SL267"></link>
	<link certainty="1.348667" xtargets="s108.2;s135.2" id="SL268"></link>
	<link certainty="1.352862" xtargets="s108.3;s135.3" id="SL269"></link>
	<link certainty="0.840275" xtargets="s108.4;s135.4" id="SL270"></link>
	<link certainty="1.590436" xtargets="s109.1;s136.1" id="SL272"></link>
	<link certainty="1.475453" xtargets="s109.2;s136.2" id="SL273"></link>
	<link certainty="1.603343" xtargets="s109.3;s136.3" id="SL274"></link>
	<link certainty="0.898701" xtargets="s109.4;s136.4" id="SL275"></link>
	<link certainty="-0.033377" xtargets="s109.5;s137.1 s138.1 s139.1" id="SL276"></link>
	<link certainty="8.92727" xtargets=";s140.1 s141.1 s142.1" id="SL277"></link>
	<link certainty="9.82727" xtargets="s110.1;s143.1" id="SL278"></link>
	<link certainty="-0.225" xtargets="s111.1;s144.1" id="SL280"></link>
	<link certainty="-0.106173" xtargets="s112.1;s145.1 s145.2 s145.3" id="SL282"></link>
	<link certainty="-0.190385" xtargets="s113.1;s146.1 s146.2" id="SL284"></link>
	<link certainty="0.225" xtargets="s114.1;s147.1" id="SL286"></link>
	<link certainty="-0.092308" xtargets=";s148.1" id="SL288"></link>
	<link certainty="0.207692" xtargets="s115.1;s148.2" id="SL289"></link>
	<link certainty="-0.21" xtargets="s116.1;s149.1" id="SL291"></link>
	<link certainty="0.208567" xtargets="s117.1;s150.1" id="SL293"></link>
	<link certainty="1.272321" xtargets="s117.2;s150.2" id="SL294"></link>
	<link certainty="0.463754" xtargets="s117.3;s150.3" id="SL295"></link>
	<link certainty="-0.3" xtargets="s118.1;s151.1" id="SL297"></link>
	<link certainty="-0.6" xtargets="s118.2;" id="SL298"></link>
	<link certainty="-0.070588" xtargets="s119.1 s119.2;s152.1" id="SL299"></link>
	<link certainty="-0.062963" xtargets="s120.1 s120.2;s152.2" id="SL300"></link>
	<link certainty="-0.066667" xtargets="s121.1;s153.1" id="SL302"></link>
	<link certainty="-0.9" xtargets="s121.2;" id="SL303"></link>
	<link certainty="0.0477270000000001" xtargets="s122.1;s154.1" id="SL304"></link>
	<link certainty="0.647727" xtargets="s122.2;s154.2" id="SL305"></link>
	<link certainty="1.968515" xtargets="s123.1;s155.1" id="SL307"></link>
	<link certainty="2.54157" xtargets="s123.2;s155.2" id="SL308"></link>
	<link certainty="1.41968" xtargets="s123.3;s155.3" id="SL309"></link>
	<link certainty="2.364185" xtargets="s124.1;s156.1" id="SL311"></link>
	<link certainty="1.41968" xtargets="s124.2;s156.2" id="SL312"></link>
	<link certainty="1.125" xtargets="s125.1;s157.1" id="SL314"></link>
	<link certainty="0.55508" xtargets="s126.1;s158.1" id="SL316"></link>
	<link certainty="4.47662" xtargets="s127.1;s159.1" id="SL318"></link>
	<link certainty="1.98883" xtargets="s127.2;s159.2" id="SL319"></link>
	<link certainty="0.584875" xtargets="s128.1;s160.1" id="SL321"></link>
	<link certainty="0.711538" xtargets="s129.1;s161.1" id="SL323"></link>
	<link certainty="1.953846" xtargets="s130.1;s162.1" id="SL325"></link>
	<link certainty="0.253846" xtargets="s130.2;s162.2" id="SL326"></link>
	<link certainty="0.987931" xtargets="s131.1;s163.1" id="SL328"></link>
	<link certainty="0.3055701" xtargets="s132.1;s164.1" id="SL330"></link>
	<link certainty="1.8142241" xtargets="s132.2;s164.2" id="SL331"></link>
	<link certainty="1.7625" xtargets="s132.3;s164.3" id="SL332"></link>
	<link certainty="1.89006" xtargets="s133.1;s165.1" id="SL334"></link>
	<link certainty="0.29542" xtargets="s133.2;s165.2" id="SL335"></link>
	<link certainty="0.275" xtargets="s134.1;s165.3" id="SL336"></link>
	<link certainty="0.864142" xtargets="s135.1;s166.1" id="SL338"></link>
	<link certainty="1.191036" xtargets="s135.2;s166.2" id="SL339"></link>
	<link certainty="0.474586" xtargets="s135.3;s166.3" id="SL340"></link>
	<link certainty="3.464302" xtargets="s136.1;s167.1" id="SL342"></link>
	<link certainty="1.367919" xtargets="s136.2;s167.2" id="SL343"></link>
	<link certainty="2.089417" xtargets="s136.3;s167.3" id="SL344"></link>
	<link certainty="3.40905" xtargets="s136.4;s167.4" id="SL345"></link>
	<link certainty="2.554545" xtargets="s136.5;s167.5" id="SL346"></link>
	<link certainty="0.635971" xtargets="s136.6 s136.7;s167.6" id="SL347"></link>
	<link certainty="0.367766" xtargets="s136.8;s167.7" id="SL348"></link>
	<link certainty="1.738093" xtargets="s137.1;s168.1" id="SL350"></link>
	<link certainty="1.00875" xtargets="s137.2;s168.2" id="SL351"></link>
	<link certainty="1.248455" xtargets="s138.1;s169.1" id="SL353"></link>
	<link certainty="0.472727" xtargets="s138.2;s169.2" id="SL354"></link>
	<link certainty="0.750097" xtargets="s139.1;s170.1" id="SL356"></link>
	<link certainty="1.437376" xtargets="s140.1;s171.1" id="SL358"></link>
	<link certainty="1.07335" xtargets="s140.2;s171.2" id="SL359"></link>
	<link certainty="1.218423" xtargets="s140.3;s171.3" id="SL360"></link>
	<link certainty="1.743144" xtargets="s140.4;s171.4" id="SL361"></link>
	<link certainty="2.16476" xtargets="s140.5;s171.5" id="SL362"></link>
	<link certainty="2.03733" xtargets="s140.6;s171.6" id="SL363"></link>
	<link certainty="1.776683" xtargets="s140.7;s171.7" id="SL364"></link>
	<link certainty="0.806683" xtargets="s140.8;s171.8" id="SL365"></link>
	<link certainty="-0.0160714" xtargets="s140.9;s172.1 s172.2" id="SL366"></link>
	<link certainty="4.15922" xtargets="s141.1;s173.1" id="SL368"></link>
	<link certainty="3.48515" xtargets="s141.2;s173.2" id="SL369"></link>
	<link certainty="1.326875" xtargets="s141.3;s173.3" id="SL370"></link>
	<link certainty="2.531085" xtargets="s141.4 s141.5;s173.4" id="SL371"></link>
	<link certainty="2.84672" xtargets="s141.6;s173.5" id="SL372"></link>
	<link certainty="2.01219" xtargets="s141.7;s173.6" id="SL373"></link>
	<link certainty="1.59506" xtargets="s141.8;s173.7" id="SL374"></link>
	<link certainty="1.089527" xtargets="s142.1;s174.1" id="SL376"></link>
	<link certainty="1.458777" xtargets="s142.2;s174.2" id="SL377"></link>
	<link certainty="0.980182" xtargets="s142.3;s174.3" id="SL378"></link>
	<link certainty="0.3" xtargets="s143.1;s175.1" id="SL380"></link>
	<link certainty="0.709369" xtargets="s144.1;s176.1" id="SL382"></link>
	<link certainty="0.288" xtargets="s144.2;s176.2" id="SL383"></link>
	<link certainty="0.606429" xtargets="s145.1;s177.1" id="SL385"></link>
	<link certainty="1.10299" xtargets="s146.1;s178.1" id="SL387"></link>
	<link certainty="1.15385" xtargets="s147.1;" id="SL388"></link>
	<link certainty="1.45385" xtargets="s148.1;s179.1" id="SL389"></link>
	<link certainty="-0.425" xtargets="s149.1;s180.1" id="SL391"></link>
	<link certainty="0.96" xtargets="s150.1;s181.1" id="SL393"></link>
	<link certainty="1.433726" xtargets="s151.1;s182.1" id="SL395"></link>
	<link certainty="0.927232" xtargets="s151.2;s182.2" id="SL396"></link>
	<link certainty="1.297376" xtargets="s152.1;s183.1" id="SL398"></link>
	<link certainty="0.436765" xtargets="s152.2 s152.3;s183.2" id="SL399"></link>
	<link certainty="3.550634" xtargets="s153.1;s184.1" id="SL401"></link>
	<link certainty="0.842754" xtargets="s153.2;s184.2" id="SL402"></link>
	<link certainty="0.796512" xtargets="s154.1;s185.1" id="SL404"></link>
	<link certainty="1.01599" xtargets="s155.1;s186.1" id="SL406"></link>
	<link certainty="0.115964" xtargets="s156.1 s156.2;s187.1" id="SL408"></link>
	<link certainty="0.292021" xtargets="s157.1 s157.2;s188.1" id="SL410"></link>
	<link certainty="0.315333" xtargets="s158.1 s158.2;s189.1" id="SL412"></link>
	<link certainty="0.206739" xtargets="s159.1 s159.2;s190.1" id="SL414"></link>
	<link certainty="4.61413" xtargets="s160.1 s160.2;" id="SL415"></link>
	<link certainty="4.91413" xtargets="s161.1;s191.1" id="SL416"></link>
	<link certainty="4.48699" xtargets="s161.2;s192.1" id="SL417"></link>
	<link certainty="1.01129" xtargets="s162.1;s193.1" id="SL419"></link>
	<link certainty="1.8" xtargets="s163.1;s194.1" id="SL421"></link>
	<link certainty="0.785417" xtargets="s164.1;s195.1" id="SL423"></link>
	<link certainty="1.329308" xtargets="s165.1;s196.1" id="SL425"></link>
	<link certainty="1.521372" xtargets="s165.2 s165.3;s196.2" id="SL426"></link>
	<link certainty="0.835612" xtargets="s165.4;s196.3" id="SL427"></link>
	<link certainty="0.470297" xtargets="s166.1;s197.1" id="SL429"></link>
	<link certainty="0" xtargets=";s198.1" id="SL430"></link>
	<link certainty="0.3" xtargets="s167.1;s199.1" id="SL431"></link>
	<link certainty="3.155938" xtargets="s168.1;s200.1" id="SL433"></link>
	<link certainty="0.977118" xtargets="s168.2;s200.2" id="SL434"></link>
	<link certainty="0.824658" xtargets="s169.1 s169.2;s200.3" id="SL435"></link>
	<link certainty="1.157222" xtargets="s169.3;s200.4" id="SL436"></link>
	<link certainty="4.770134" xtargets="s169.4;s200.5" id="SL437"></link>
	<link certainty="4.26757" xtargets="s169.5;s200.6" id="SL438"></link>
	<link certainty="-0.115385" xtargets=";s201.1" id="SL439"></link>
	<link certainty="0.184615" xtargets="s170.1;s202.1" id="SL440"></link>
	<link certainty="2.75325" xtargets="s171.1;s203.1" id="SL442"></link>
	<link certainty="0.150769" xtargets=";s204.1" id="SL443"></link>
	<link certainty="1.114453" xtargets="s172.1;s205.1" id="SL444"></link>
	<link certainty="2.262334" xtargets="s172.2;s205.2" id="SL445"></link>
	<link certainty="2.293075" xtargets="s172.3;s205.3" id="SL446"></link>
	<link certainty="1.766985" xtargets="s172.4;s205.4" id="SL447"></link>
	<link certainty="1.07256" xtargets="s172.5;s205.5" id="SL448"></link>
	<link certainty="1.407167" xtargets="s173.1;s206.1" id="SL450"></link>
	<link certainty="0.856579" xtargets="s173.2;s206.2" id="SL451"></link>
	<link certainty="2.03825" xtargets="s174.1;s207.1" id="SL453"></link>
	<link certainty="1.32377" xtargets="s174.2;s207.2" id="SL454"></link>
	<link certainty="1.91946" xtargets=";s208.1" id="SL455"></link>
	<link certainty="3.154362" xtargets="s175.1;s209.1" id="SL456"></link>
	<link certainty="3.224462" xtargets="s175.2;s209.2" id="SL457"></link>
	<link certainty="2.28956" xtargets="s175.3;s209.3" id="SL458"></link>
	<link certainty="2.28555" xtargets=";s210.1" id="SL459"></link>
	<link certainty="2.58555" xtargets="s176.1;s211.1" id="SL460"></link>
	<link certainty="0.74548" xtargets=";s212.1" id="SL461"></link>
	<link certainty="1.509116" xtargets="s177.1;s213.1" id="SL462"></link>
	<link certainty="0.463636" xtargets="s177.2;s213.2" id="SL463"></link>
	<link certainty="0.369412" xtargets=";s214.1" id="SL464"></link>
	<link certainty="1.090633" xtargets="s178.1;s215.1" id="SL465"></link>
	<link certainty="0.421221" xtargets="s178.2;s215.2" id="SL466"></link>
	<link certainty="0" xtargets=";s216.1" id="SL467"></link>
	<link certainty="0.3" xtargets="s179.1;s217.1" id="SL468"></link>
	<link certainty="2.79748" xtargets="s180.1;s218.1" id="SL470"></link>
	<link certainty="2.279401" xtargets="s180.2 s180.3;s218.2" id="SL471"></link>
	<link certainty="0.973881" xtargets="s180.4;s218.3" id="SL472"></link>
	<link certainty="0.850988" xtargets="s181.1;s219.1" id="SL474"></link>
	<link certainty="0.959772" xtargets="s181.2;s219.2" id="SL475"></link>
	<link certainty="2.802993" xtargets="s181.3;s219.3" id="SL476"></link>
	<link certainty="2.12583" xtargets="s181.4;s219.4" id="SL477"></link>
	<link certainty="2.579718" xtargets="s182.1;s220.1" id="SL479"></link>
	<link certainty="3.32074" xtargets="s182.2;s220.2" id="SL480"></link>
	<link certainty="1.13333" xtargets="s182.3;s220.3" id="SL481"></link>
	<link certainty="-0.194118" xtargets=";s221.1" id="SL482"></link>
	<link certainty="0.405882" xtargets="s183.1;s222.1" id="SL483"></link>
	<link certainty="0.918243" xtargets="s183.2;s222.2" id="SL484"></link>
	<link certainty="0.880743" xtargets="s183.3;s222.3" id="SL485"></link>
	<link certainty="4.72614" xtargets="s183.4;s222.4" id="SL486"></link>
	<link certainty="4.46364" xtargets="s183.5;s222.5" id="SL487"></link>
	<link certainty="0.175833" xtargets=";s223.1" id="SL488"></link>
	<link certainty="1.467296" xtargets="s184.1;s224.1" id="SL489"></link>
	<link certainty="0.991463" xtargets="s184.2;s224.2" id="SL490"></link>
	<link certainty="0.509248" xtargets=";s225.1" id="SL491"></link>
	<link certainty="1.701556" xtargets="s185.1;s226.1" id="SL492"></link>
	<link certainty="1.200135" xtargets="s185.2;s226.2" id="SL493"></link>
	<link certainty="0.307827" xtargets="s185.3 s185.4;s226.3" id="SL494"></link>
	<link certainty="0.78" xtargets="s186.1;s227.1" id="SL496"></link>
	<link certainty="1.322008" xtargets="s187.1;s228.1" id="SL498"></link>
	<link certainty="0.306038" xtargets="s187.2 s187.3;s228.2" id="SL499"></link>
	<link certainty="0.230769" xtargets="s188.1;s229.1" id="SL501"></link>
	<link certainty="1.295385" xtargets="s189.1;s230.1" id="SL503"></link>
	<link certainty="0.723854" xtargets="s189.2;s230.2" id="SL504"></link>
	<link certainty="0.718855" xtargets="s189.3;s230.3" id="SL505"></link>
	<link certainty="1.19684" xtargets="s189.4;s230.4" id="SL506"></link>
	<link certainty="0.601318" xtargets="s189.5;s230.5" id="SL507"></link>
	<link certainty="4.04211" xtargets="s190.1;s231.1" id="SL509"></link>
	<link certainty="3.14811" xtargets="s190.2;s231.2" id="SL510"></link>
	<link certainty="1.00208" xtargets="s191.1 s191.2;s231.3" id="SL511"></link>
	<link certainty="2.4466" xtargets="s191.3;s231.4" id="SL512"></link>
	<link certainty="2.17785" xtargets="s191.4;s231.5" id="SL513"></link>
	<link certainty="2.11752" xtargets="s192.1;s232.1" id="SL515"></link>
	<link certainty="1.03333" xtargets="s192.2;s232.2" id="SL516"></link>
	<link certainty="0.27" xtargets="s193.1;s233.1" id="SL518"></link>
	<link certainty="0.421809" xtargets="s194.1;s234.1" id="SL520"></link>
	<link certainty="2.06087" xtargets="s195.1;s235.1" id="SL522"></link>
	<link certainty="0.26087" xtargets="s195.2;s235.2" id="SL523"></link>
	<link certainty="0.705" xtargets="s196.1;s236.1" id="SL525"></link>
	<link certainty="0.229306" xtargets="s197.1;s237.1 s237.2" id="SL527"></link>
	<link certainty="2.40083" xtargets="s198.1;s238.1 s238.2" id="SL529"></link>
	<link certainty="1.27143" xtargets="s199.1;s239.1" id="SL531"></link>
	<link certainty="0.26" xtargets="s200.1;s240.1" id="SL533"></link>
	<link certainty="0.819231" xtargets="s201.1;s241.1" id="SL535"></link>
	<link certainty="9.3" xtargets="s202.1;s242.1" id="SL537"></link>
	<link certainty="1.12187" xtargets="s203.1;s243.1" id="SL539"></link>
	<link certainty="0.842857" xtargets="s204.1;s244.1" id="SL541"></link>
	<link certainty="0.709821" xtargets="s205.1;s245.1" id="SL543"></link>
	<link certainty="2.85925" xtargets="s206.1;s246.1" id="SL545"></link>
	<link certainty="-0.1" xtargets="s207.1;s247.1" id="SL547"></link>
	<link certainty="1.14545" xtargets="s208.1;s248.1" id="SL549"></link>
	<link certainty="0.208696" xtargets="s209.1;s249.1" id="SL551"></link>
	<link certainty="1.765" xtargets="s210.1;s250.1" id="SL553"></link>
	<link certainty="0.165" xtargets="s210.2;s250.2" id="SL554"></link>
	<link certainty="4.26897" xtargets="s211.1;s251.1" id="SL556"></link>
	<link certainty="1.92" xtargets="s212.1;s252.1" id="SL558"></link>
	<link certainty="0.12" xtargets="s212.2;s252.2" id="SL559"></link>
	<link certainty="0.3" xtargets="s213.1;s253.1" id="SL561"></link>
	<link certainty="2.82059" xtargets="s214.1;s254.1" id="SL563"></link>
	<link certainty="1.02059" xtargets="s214.2;s254.2" id="SL564"></link>
	<link certainty="0.466667" xtargets="s215.1 s215.2;s255.1" id="SL566"></link>
	<link certainty="1.29" xtargets="s216.1;s256.1" id="SL568"></link>
	<link certainty="0.99" xtargets="s216.2;s256.2" id="SL569"></link>
	<link certainty="1.02" xtargets="s217.1;s257.1" id="SL571"></link>
	<link certainty="2.395" xtargets="s218.1;s258.1" id="SL573"></link>
	<link certainty="0.595" xtargets="s218.2;s258.2" id="SL574"></link>
	<link certainty="2.513158" xtargets="s219.1;s259.1" id="SL576"></link>
	<link certainty="0.713158" xtargets="s219.2;s259.2" id="SL577"></link>
	<link certainty="1.895" xtargets="s220.1;s260.1" id="SL579"></link>
	<link certainty="0.595" xtargets="s220.2;s260.2" id="SL580"></link>
	<link certainty="0.769183" xtargets="s221.1;s261.1" id="SL582"></link>
	<link certainty="2.19906" xtargets="s222.1 s222.2;s262.1" id="SL584"></link>
	<link certainty="2.75" xtargets="s223.1;s263.1" id="SL586"></link>
	<link certainty="6.68723" xtargets="s224.1;s264.1" id="SL588"></link>
	<link certainty="5.38723" xtargets="s224.2;s264.2" id="SL589"></link>
	<link certainty="0.725448" xtargets="s225.1;s265.1" id="SL591"></link>
	<link certainty="2.513158" xtargets="s226.1;s266.1" id="SL593"></link>
	<link certainty="0.713158" xtargets="s226.2;s266.2" id="SL594"></link>
	<link certainty="0.568539" xtargets="s227.1;s267.1" id="SL596"></link>
	<link certainty="0.26087" xtargets="s228.1;s268.1" id="SL598"></link>
	<link certainty="0.718165" xtargets="s229.1;s269.1" id="SL600"></link>
	<link certainty="1.48689" xtargets=";s270.1" id="SL601"></link>
	<link certainty="1.78689" xtargets="s230.1;s271.1" id="SL602"></link>
	<link certainty="0.717135" xtargets="s231.1;s272.1" id="SL604"></link>
	<link certainty="1.67106" xtargets="s232.1;s273.1" id="SL606"></link>
	<link certainty="0.868111" xtargets="s233.1;s274.1" id="SL608"></link>
	<link certainty="1.02273" xtargets="s234.1;s275.1" id="SL610"></link>
	<link certainty="0.244444" xtargets="s235.1;s276.1" id="SL612"></link>
	<link certainty="1.48" xtargets="s236.1;s277.1" id="SL614"></link>
	<link certainty="0.18" xtargets="s236.2;s277.2" id="SL615"></link>
	<link certainty="0.248571" xtargets="s237.1;s278.1" id="SL617"></link>
	<link certainty="-0.0428571" xtargets="s238.1;s279.1" id="SL619"></link>
	<link certainty="2.82692" xtargets="s239.1;s280.1" id="SL621"></link>
	<link certainty="1.02692" xtargets="s239.2;s280.2" id="SL622"></link>
	<link certainty="1.75455" xtargets="s240.1;s281.1" id="SL624"></link>
	<link certainty="1.14514" xtargets="s241.1;s282.1" id="SL626"></link>
	<link certainty="1.581818" xtargets="s242.1;s283.1" id="SL628"></link>
	<link certainty="-0.218182" xtargets="s242.2;s283.2" id="SL629"></link>
	<link certainty="3.675" xtargets="s243.1;s284.1" id="SL631"></link>
	<link certainty="2.029412" xtargets="s244.1;s285.1" id="SL633"></link>
	<link certainty="0.229412" xtargets="s244.2;s285.2" id="SL634"></link>
	<link certainty="2.053846" xtargets="s245.1;s286.1" id="SL636"></link>
	<link certainty="0.253846" xtargets="s245.2;s286.2" id="SL637"></link>
	<link certainty="4.65599" xtargets="s246.1;s287.1" id="SL639"></link>
	<link certainty="2.488571" xtargets="s247.1;s288.1" id="SL641"></link>
	<link certainty="0.688571" xtargets="s247.2;s288.2" id="SL642"></link>
	<link certainty="1.216" xtargets="s248.1;s289.1" id="SL644"></link>
	<link certainty="0.966" xtargets="s248.2;s289.2" id="SL645"></link>
	<link certainty="2.510053" xtargets="s249.1;s290.1" id="SL647"></link>
	<link certainty="0.710053" xtargets="s249.2;s290.2" id="SL648"></link>
	<link certainty="0.210811" xtargets="s250.1;s291.1" id="SL650"></link>
	<link certainty="2.074286" xtargets="s251.1;s292.1" id="SL652"></link>
	<link certainty="0.274286" xtargets="s251.2;s292.2" id="SL653"></link>
	<link certainty="2.045455" xtargets="s252.1;s293.1" id="SL655"></link>
	<link certainty="0.245455" xtargets="s252.2;s293.2" id="SL656"></link>
	<link certainty="2.025" xtargets="s253.1;s294.1" id="SL658"></link>
	<link certainty="1.8" xtargets="s253.2;s294.2" id="SL659"></link>
	<link certainty="1.576" xtargets="s254.1;s295.1" id="SL661"></link>
	<link certainty="0.276" xtargets="s254.2;s295.2" id="SL662"></link>
	<link certainty="0.771795" xtargets="s255.1;s296.1" id="SL664"></link>
	<link certainty="0.471795" xtargets="s255.2;s296.2" id="SL665"></link>
	<link certainty="1.45714" xtargets="s256.1;s297.1" id="SL667"></link>
	<link certainty="1.15714" xtargets="s256.2;s297.2" id="SL668"></link>
	<link certainty="4.26897" xtargets="s257.1;s298.1" id="SL670"></link>
	<link certainty="0.42" xtargets="s258.1;s299.1" id="SL672"></link>
	<link certainty="0.12" xtargets="s258.2;s299.2" id="SL673"></link>
	<link certainty="2.2038" xtargets="s259.1;s300.1" id="SL675"></link>
	<link certainty="0.425" xtargets="s260.1;s301.1" id="SL677"></link>
	<link certainty="0.125" xtargets="s260.2;s301.2" id="SL678"></link>
	<link certainty="1.9125" xtargets="s261.1;s302.1" id="SL680"></link>
	<link certainty="1.8" xtargets="s261.2;s302.2" id="SL681"></link>
	<link certainty="-0.3" xtargets=";s303.1 s303.2 s304.1" id="SL682"></link>
	<link certainty="0.583333" xtargets="s262.1;s305.1" id="SL683"></link>
	<link certainty="0.283333" xtargets="s262.2;s305.2" id="SL684"></link>
	<link certainty="-0.006" xtargets="s263.1;s306.1 s306.2" id="SL686"></link>
	<link certainty="4.6" xtargets="s264.1 s264.2;s307.1" id="SL688"></link>
	<link certainty="-0.344681" xtargets="s265.1 s265.2 s266.1;" id="SL689"></link>
	<link certainty="0.255319" xtargets="s267.1;s308.1" id="SL690"></link>
	<link certainty="0.0375" xtargets="s268.1;s309.1" id="SL692"></link>
	<link certainty="2.82692" xtargets="s269.1;s310.1" id="SL694"></link>
	<link certainty="1.02692" xtargets="s269.2;s310.2" id="SL695"></link>
	<link certainty="1.73333" xtargets="s270.1;s311.1" id="SL697"></link>
	<link certainty="1.5784" xtargets="s271.1;s312.1" id="SL699"></link>
	<link certainty="3.28333" xtargets="s272.1;s313.1" id="SL701"></link>
	<link certainty="1.48333" xtargets="s272.2;s313.2" id="SL702"></link>
	<link certainty="1.5" xtargets="s273.1;s314.1" id="SL704"></link>
	<link certainty="2.045455" xtargets="s274.1;s315.1" id="SL706"></link>
	<link certainty="0.245455" xtargets="s274.2;s315.2" id="SL707"></link>
	<link certainty="2.04" xtargets="s275.1;s316.1" id="SL709"></link>
	<link certainty="1.8" xtargets="s275.2;s316.2" id="SL710"></link>
	<link certainty="1.925" xtargets="s276.1;s317.1" id="SL712"></link>
	<link certainty="0.125" xtargets="s276.2;s317.2" id="SL713"></link>
	<link certainty="1.8428571" xtargets="s277.1;s318.1" id="SL715"></link>
	<link certainty="1.8" xtargets="s277.2;s318.2" id="SL716"></link>
	<link certainty="1.84" xtargets="s278.1;s319.1" id="SL718"></link>
	<link certainty="0.04" xtargets="s278.2;s319.2" id="SL719"></link>
	<link certainty="2.68508" xtargets="s279.1;s320.1" id="SL721"></link>
	<link certainty="1.58" xtargets="s280.1;s321.1" id="SL723"></link>
	<link certainty="0.28" xtargets="s280.2;s321.2" id="SL724"></link>
	<link certainty="-0.1" xtargets="s281.1;s322.1" id="SL726"></link>
	<link certainty="5.01364" xtargets="s281.2 s282.1;s322.2" id="SL727"></link>
	<link certainty="1.78235" xtargets="s283.1;s323.1" id="SL729"></link>
	<link certainty="0.338095" xtargets="s284.1;s324.1" id="SL731"></link>
	<link certainty="1.09067" xtargets="s285.1;s325.1" id="SL733"></link>
	<link certainty="0.024" xtargets="s285.2;s325.2" id="SL734"></link>
	<link certainty="1.22632" xtargets="s286.1;s326.1" id="SL736"></link>
	<link certainty="0.4548441" xtargets="s287.1;s327.1" id="SL738"></link>
	<link certainty="-0.0521739" xtargets="s287.2;s327.2 s327.3" id="SL739"></link>
	<link certainty="0.264706" xtargets="s288.1;s328.1" id="SL741"></link>
	<link certainty="1.42692" xtargets="s289.1;s329.1" id="SL743"></link>
	<link certainty="0.701471" xtargets="s290.1;s330.1" id="SL745"></link>
	<link certainty="2.36" xtargets="s291.1;s331.1" id="SL747"></link>
	<link certainty="2.65" xtargets="s291.2;s331.2" id="SL748"></link>
	<link certainty="0.8206667" xtargets="s291.3;s331.3" id="SL749"></link>
	<link certainty="0.6706667" xtargets="s291.4 s291.5 s291.6;s331.4" id="SL750"></link>
	<link certainty="0.7431373" xtargets="s291.7;s331.5" id="SL751"></link>
	<link certainty="-0.2568627" xtargets="s291.8 s291.9 s291.10;s331.6" id="SL752"></link>
	<link certainty="-0.031579" xtargets="s291.11 s291.12 s291.13;s331.7" id="SL753"></link>
	<link certainty="2.329412" xtargets="s292.1;s332.1" id="SL755"></link>
	<link certainty="0.529412" xtargets="s292.2;s332.2" id="SL756"></link>
	<link certainty="3.529593" xtargets="s293.1;s333.1" id="SL758"></link>
	<link certainty="0.232653" xtargets="s293.2;s333.2" id="SL759"></link>
	<link certainty="0.552261" xtargets="s294.1;s334.1" id="SL761"></link>
	<link certainty="2.36087" xtargets="s295.1;s335.1" id="SL763"></link>
	<link certainty="0.56087" xtargets="s295.2;s335.2" id="SL764"></link>
	<link certainty="1.06" xtargets="s296.1;s336.1" id="SL766"></link>
	<link certainty="1.41786" xtargets="s297.1;s337.1" id="SL768"></link>
	<link certainty="0.683333" xtargets="s298.1;s338.1" id="SL770"></link>
	<link certainty="0.45" xtargets="s299.1;s339.1" id="SL772"></link>
	<link certainty="0.680519" xtargets="s300.1;s340.1" id="SL774"></link>
	<link certainty="0.221739" xtargets="s301.1;s341.1" id="SL776"></link>
	<link certainty="0.5" xtargets="s302.1;s342.1" id="SL778"></link>
	<link certainty="0.831157" xtargets="s303.1;s343.1" id="SL780"></link>
	<link certainty="1.28462" xtargets="s304.1;s344.1" id="SL782"></link>
	<link certainty="-0.518182" xtargets="s305.1;s345.1" id="SL784"></link>
	<link certainty="1.01129" xtargets="s306.1;s346.1" id="SL786"></link>
	<link certainty="1.16047" xtargets="s307.1;s347.1" id="SL788"></link>
	<link certainty="0.14" xtargets="s308.1;s348.1 s348.2" id="SL790"></link>
	<link certainty="0.12607" xtargets="s309.1 s309.2;s349.1" id="SL792"></link>
	<link certainty="1.15882" xtargets="s310.1;s350.1" id="SL794"></link>
	<link certainty="0.125" xtargets="s311.1;s351.1 s351.2" id="SL796"></link>
	<link certainty="0.502597" xtargets="s312.1;s352.1" id="SL798"></link>
	<link certainty="-0.6" xtargets="s313.1;s353.1" id="SL800"></link>
	<link certainty="1.05" xtargets="s314.1;s354.1" id="SL802"></link>
	<link certainty="0.366667" xtargets=";s355.1" id="SL803"></link>
	<link certainty="0.666667" xtargets="s315.1;s356.1" id="SL804"></link>
	<link certainty="0.670972" xtargets="s316.1;s357.1" id="SL806"></link>
	<link certainty="0.678333" xtargets="s317.1;s358.1" id="SL808"></link>
	<link certainty="0.182143" xtargets="s317.2;s358.2" id="SL809"></link>
	<link certainty="-0.012766" xtargets="s318.1;s359.1" id="SL811"></link>
	<link certainty="2.77779" xtargets="s319.1;s360.1" id="SL813"></link>
	<link certainty="1.10675" xtargets="s320.1;s361.1" id="SL815"></link>
	<link certainty="1.38355" xtargets="s321.1;s362.1" id="SL817"></link>
	<link certainty="1.73651" xtargets="s321.2;s362.2" id="SL818"></link>
	<link certainty="0.898415" xtargets="s321.3;s362.3" id="SL819"></link>
	<link certainty="0.597072" xtargets="s322.1;" id="SL821"></link>
	<link certainty="1.385799" xtargets="s322.2;s363.1" id="SL822"></link>
	<link certainty="1.165043" xtargets="s322.3;s363.2" id="SL823"></link>
	<link certainty="0.676316" xtargets="s322.4;s363.3" id="SL824"></link>
	<link certainty="0.0525714" xtargets="s323.1;s364.1" id="SL826"></link>
	<link certainty="0.0285714" xtargets="s323.2;s364.2" id="SL827"></link>
	<link certainty="3.15789" xtargets="s324.1;s365.1" id="SL829"></link>
	<link certainty="1.35789" xtargets="s324.2;s365.2" id="SL830"></link>
	<link certainty="2" xtargets="s325.1;s366.1" id="SL832"></link>
	<link certainty="2.04" xtargets="s325.2;s366.2" id="SL833"></link>
	<link certainty="1.692291" xtargets="s325.3;s366.3" id="SL834"></link>
	<link certainty="0.852291" xtargets="s325.4;s366.4" id="SL835"></link>
	<link certainty="0.798701" xtargets="s326.1;s367.1" id="SL837"></link>
	<link certainty="0.960073" xtargets="s327.1;s368.1" id="SL839"></link>
	<link certainty="0.828008" xtargets="s328.1;s369.1" id="SL841"></link>
	<link certainty="3.34067" xtargets="s329.1;s370.1" id="SL843"></link>
	<link certainty="1.30983" xtargets="s329.2;s370.2" id="SL844"></link>
	<link certainty="2.169006" xtargets="s330.1;s371.1" id="SL846"></link>
	<link certainty="0.784746" xtargets="s330.2;s371.2" id="SL847"></link>
	<link certainty="1.311475" xtargets="s331.1;s372.1" id="SL849"></link>
	<link certainty="1.444119" xtargets="s331.2;s372.2" id="SL850"></link>
	<link certainty="0.837452" xtargets="s331.3;s372.3" id="SL851"></link>
	<link certainty="1.99733" xtargets="s332.1;s373.1" id="SL853"></link>
	<link certainty="1.09733" xtargets="s332.2;s373.2" id="SL854"></link>
	<link certainty="1.443507" xtargets="s333.1;s374.1" id="SL856"></link>
	<link certainty="1.658774" xtargets="s333.2;s374.2" id="SL857"></link>
	<link certainty="1.400981" xtargets="s333.3;s374.3" id="SL858"></link>
	<link certainty="0.328571" xtargets="s333.4;s374.4" id="SL859"></link>
	<link certainty="0.937185" xtargets="s334.1;s375.1" id="SL861"></link>
	<link certainty="0.38169" xtargets="s334.2;s375.2" id="SL862"></link>
	<link certainty="1.2994" xtargets="s335.1;s376.1" id="SL864"></link>
	<link certainty="1.89" xtargets="s336.1;s377.1" id="SL866"></link>
	<link certainty="0.09" xtargets="s336.2;s377.2" id="SL867"></link>
	<link certainty="0.558498" xtargets="s337.1;s378.1" id="SL869"></link>
	<link certainty="0.914984" xtargets="s338.1;s379.1" id="SL871"></link>
	<link certainty="1.000352" xtargets="s339.1;s380.1" id="SL873"></link>
	<link certainty="1.077901" xtargets="s339.2;s380.2" id="SL874"></link>
	<link certainty="0.717364" xtargets="s339.3;s380.3" id="SL875"></link>
	<link certainty="1.21371" xtargets="s340.1;s381.1" id="SL877"></link>
	<link certainty="0.61371" xtargets="s340.2;s381.2" id="SL878"></link>
	<link certainty="4.71886" xtargets="s341.1;s382.1" id="SL880"></link>
	<link certainty="1.12353" xtargets="s342.1;s383.1" id="SL882"></link>
	<link certainty="1.275" xtargets="s343.1;s384.1" id="SL884"></link>
	<link certainty="1.03" xtargets="s344.1;s385.1" id="SL886"></link>
	<link certainty="1.16" xtargets="s345.1;s386.1" id="SL888"></link>
	<link certainty="1.28125" xtargets="s346.1;s387.1" id="SL890"></link>
	<link certainty="1.27" xtargets="s347.1;s388.1" id="SL892"></link>
	<link certainty="1.27273" xtargets="s348.1;s389.1" id="SL894"></link>
	<link certainty="0.364286" xtargets="s349.1;s390.1" id="SL896"></link>
	<link certainty="1.69481" xtargets=";s391.1" id="SL897"></link>
	<link certainty="1.99481" xtargets="s350.1;s392.1" id="SL898"></link>
	<link certainty="1.27273" xtargets="s351.1;s393.1" id="SL900"></link>
	<link certainty="1.175" xtargets="s352.1;s394.1" id="SL902"></link>
	<link certainty="4.62939" xtargets=";s395.1" id="SL903"></link>
	<link certainty="4.92939" xtargets="s353.1;s396.1" id="SL904"></link>
	<link certainty="0.743478" xtargets="s354.1;s397.1" id="SL906"></link>
	<link certainty="1.36667" xtargets="s355.1;s398.1" id="SL908"></link>
	<link certainty="1.09211" xtargets="s356.1;s399.1" id="SL910"></link>
	<link certainty="0.2" xtargets="s357.1;s400.1" id="SL912"></link>
	<link certainty="1.19091" xtargets="s358.1;s401.1" id="SL914"></link>
	<link certainty="1.5" xtargets="s359.1;" id="SL915"></link>
	<link certainty="3.15" xtargets="s360.1;s402.1" id="SL916"></link>
	<link certainty="1.35" xtargets="s360.2;s402.2" id="SL917"></link>
	<link certainty="0.210811" xtargets="s361.1;s403.1" id="SL919"></link>
	<link certainty="0.289202" xtargets="s362.1;s404.1" id="SL921"></link>
	<link certainty="0.82381" xtargets="s363.1;s405.1" id="SL923"></link>
	<link certainty="0.891425" xtargets="s364.1;s406.1" id="SL925"></link>
	<link certainty="0.652198" xtargets="s364.2;s406.2" id="SL926"></link>
	<link certainty="0.271429" xtargets="s364.3;s406.3" id="SL927"></link>
	<link certainty="1.868421" xtargets="s365.1;s407.1" id="SL929"></link>
	<link certainty="0.268421" xtargets="s365.2;s407.2" id="SL930"></link>
	<link certainty="3.29189" xtargets="s366.1;s408.1" id="SL932"></link>
	<link certainty="0.54" xtargets="s366.2;s409.1" id="SL933"></link>
	<link certainty="5.30341" xtargets="s367.1;s410.1" id="SL935"></link>
	<link certainty="3.01697" xtargets="s367.2;s410.2" id="SL936"></link>
	<link certainty="3.825669" xtargets="s368.1;s411.1" id="SL938"></link>
	<link certainty="3.54306" xtargets="s368.2;s411.2" id="SL939"></link>
	<link certainty="2.23327" xtargets="s369.1;s412.1" id="SL941"></link>
	<link certainty="5.58983" xtargets="s369.2;s412.2" id="SL942"></link>
	<link certainty="3.60656" xtargets="s369.3;s412.3" id="SL943"></link>
	<link certainty="3.67008" xtargets="s370.1;s412.4" id="SL944"></link>
	<link certainty="0.65177" xtargets="s371.1;s413.1" id="SL946"></link>
	<link certainty="3.87143" xtargets="s372.1;s414.1" id="SL948"></link>
	<link certainty="3.87143" xtargets="s373.1;s415.1" id="SL950"></link>
	<link certainty="3.65217" xtargets="s374.1;" id="SL951"></link>
	<link certainty="3.95217" xtargets="s375.1;s416.1" id="SL952"></link>
	<link certainty="4.01429" xtargets="s376.1;s417.1" id="SL954"></link>
	<link certainty="8.7" xtargets="s377.1;s418.1" id="SL956"></link>
	<link certainty="6.3" xtargets="s377.2;s418.2" id="SL957"></link>
	<link certainty="5.14615" xtargets="s378.1;s419.1" id="SL959"></link>
	<link certainty="4.15714" xtargets="s379.1;s420.1" id="SL961"></link>
	<link certainty="7.50909" xtargets="s380.1;s421.1" id="SL963"></link>
	<link certainty="5.20909" xtargets="s380.2;s421.2" id="SL964"></link>
	<link certainty="4.8" xtargets="s381.1;s422.1" id="SL966"></link>
	<link certainty="4.15714" xtargets="s382.1;s423.1" id="SL968"></link>
	<link certainty="2.69562" xtargets="s383.1;s424.1" id="SL970"></link>
	<link certainty="7.15909" xtargets="s384.1;s425.1" id="SL972"></link>
	<link certainty="5.20909" xtargets="s384.2;s425.2" id="SL973"></link>
	<link certainty="8.87472" xtargets="s385.1;s426.1" id="SL975"></link>
	<link certainty="6.72857" xtargets="s385.2;s426.2" id="SL976"></link>
	<link certainty="3.98182" xtargets="s386.1;s427.1" id="SL978"></link>
	<link certainty="6.9738" xtargets="s387.1;s428.1" id="SL980"></link>
	<link certainty="5.20909" xtargets="s387.2;s428.2" id="SL981"></link>
	<link certainty="4.6125" xtargets="s388.1;s429.1" id="SL983"></link>
	<link certainty="5.14615" xtargets="s389.1;s430.1" id="SL985"></link>
	<link certainty="9.6" xtargets="s390.1;s431.1" id="SL987"></link>
	<link certainty="7.3" xtargets="s390.2;s431.2" id="SL988"></link>
	<link certainty="5.14615" xtargets="s391.1;s432.1" id="SL990"></link>
	<link certainty="8.36667" xtargets="s392.1;s433.1" id="SL992"></link>
	<link certainty="5.96667" xtargets="s392.2;s433.2" id="SL993"></link>
	<link certainty="8.88235" xtargets="s393.1;s434.1" id="SL995"></link>
	<link certainty="6.78235" xtargets="s393.2;s434.2" id="SL996"></link>
	<link certainty="8.475" xtargets="s394.1;s435.1" id="SL998"></link>
	<link certainty="6.3" xtargets="s394.2;s435.2" id="SL999"></link>
	<link certainty="5.14615" xtargets="s395.1;s436.1" id="SL1001"></link>
	<link certainty="4.68462" xtargets="s396.1;s437.1" id="SL1003"></link>
	<link certainty="4.08261" xtargets="s397.1;s438.1" id="SL1005"></link>
	<link certainty="4.15714" xtargets="s398.1;s439.1" id="SL1007"></link>
	<link certainty="2.97576" xtargets="s399.1;s440.1" id="SL1009"></link>
	<link certainty="5.01429" xtargets="s400.1;s441.1" id="SL1011"></link>
	<link certainty="4.8" xtargets="s401.1;s442.1" id="SL1013"></link>
	<link certainty="1.00286" xtargets="s402.1;s443.1" id="SL1015"></link>
	<link certainty="0.864338" xtargets="s403.1;s444.1" id="SL1017"></link>
	<link certainty="0.6" xtargets="s404.1;s445.1" id="SL1019"></link>
</linkGrp><?xml version="1.0" encoding="utf-8"?>
<linkGrp targType="s" toDoc="en/humandocs/PDFs/EPAR/competact/H-655-PI-en.xml.gz" fromDoc="de/humandocs/PDFs/EPAR/competact/H-655-PI-de.xml.gz">
	<link certainty="1.25714" xtargets="s1.1;s1.1" id="SL2"></link>
	<link certainty="0.796875" xtargets="s2.1;s2.1" id="SL4"></link>
	<link certainty="13.32692" xtargets="s3.1;s3.1" id="SL6"></link>
	<link certainty="1.02692" xtargets="s3.2;s3.2" id="SL7"></link>
	<link certainty="1.5416" xtargets="s4.1;s4.1" id="SL9"></link>
	<link certainty="3.26842" xtargets="s5.1;s5.1" id="SL11"></link>
	<link certainty="1.46842" xtargets="s5.2;s5.2" id="SL12"></link>
	<link certainty="3.66054" xtargets="s6.1;s6.1" id="SL14"></link>
	<link certainty="0.900682" xtargets="s7.1;s7.1" id="SL16"></link>
	<link certainty="2.064706" xtargets="s8.1;s8.1" id="SL18"></link>
	<link certainty="0.264706" xtargets="s8.2;s8.2" id="SL19"></link>
	<link certainty="0.184615" xtargets="s9.1;s9.1" id="SL21"></link>
	<link certainty="2.58412" xtargets="s10.1;s10.1" id="SL23"></link>
	<link certainty="2.047059" xtargets="s11.1;s11.1" id="SL25"></link>
	<link certainty="0.247059" xtargets="s11.2;s11.2" id="SL26"></link>
	<link certainty="1.22857" xtargets="s12.1;s12.1" id="SL28"></link>
	<link certainty="1.95736" xtargets="s13.1;s13.1" id="SL30"></link>
	<link certainty="0.728571" xtargets="s14.1;s14.1" id="SL32"></link>
	<link certainty="1.16124" xtargets=";s15.1" id="SL33"></link>
	<link certainty="1.46124" xtargets="s15.1;s16.1" id="SL34"></link>
	<link certainty="0.8825" xtargets="s16.1;s17.1" id="SL36"></link>
	<link certainty="0.993333" xtargets="s17.1;s18.1" id="SL38"></link>
	<link certainty="1.70426" xtargets="s18.1;s19.1" id="SL40"></link>
	<link certainty="0.688704" xtargets=";s20.1" id="SL41"></link>
	<link certainty="0.988704" xtargets="s19.1;s21.1" id="SL42"></link>
	<link certainty="2.25018" xtargets=";s22.1" id="SL43"></link>
	<link certainty="2.55018" xtargets="s20.1;s23.1" id="SL44"></link>
	<link certainty="1.00493" xtargets=";s24.1" id="SL45"></link>
	<link certainty="1.30493" xtargets="s21.1;s25.1" id="SL46"></link>
	<link certainty="0.7648" xtargets=";s26.1" id="SL47"></link>
	<link certainty="1.0648" xtargets="s22.1;s27.1" id="SL48"></link>
	<link certainty="1.22941" xtargets="s23.1;s28.1" id="SL50"></link>
	<link certainty="1.03571" xtargets="s24.1;s29.1" id="SL52"></link>
	<link certainty="0.786438" xtargets="s25.1;s30.1" id="SL54"></link>
	<link certainty="1.88464" xtargets="s26.1;s31.1" id="SL56"></link>
	<link certainty="0.83791" xtargets="s27.1;" id="SL57"></link>
	<link certainty="1.13791" xtargets="s28.1;s32.1" id="SL58"></link>
	<link certainty="-0.136364" xtargets="s29.1;s33.1" id="SL60"></link>
	<link certainty="1.18947" xtargets="s30.1;s34.1" id="SL62"></link>
	<link certainty="0.775676" xtargets="s31.1;s35.1" id="SL64"></link>
	<link certainty="1.08964" xtargets="s32.1;s36.1" id="SL66"></link>
	<link certainty="4.20385" xtargets="s33.1;s37.1" id="SL68"></link>
	<link certainty="0.652308" xtargets="s34.1;" id="SL69"></link>
	<link certainty="0.952308" xtargets="s35.1;s38.1" id="SL70"></link>
	<link certainty="1.25385" xtargets="s36.1;s39.1" id="SL72"></link>
	<link certainty="0.997059" xtargets="s37.1;s40.1" id="SL74"></link>
	<link certainty="1.25714" xtargets="s38.1;s41.1" id="SL76"></link>
	<link certainty="1.37245" xtargets="s39.1;s42.1" id="SL78"></link>
	<link certainty="1.3" xtargets="s40.1;s43.1" id="SL80"></link>
	<link certainty="1.24038" xtargets="s41.1;s44.1" id="SL82"></link>
	<link certainty="1.13397" xtargets="s42.1;s45.1" id="SL84"></link>
	<link certainty="0.312245" xtargets=";s46.1" id="SL85"></link>
	<link certainty="1.451864" xtargets="s43.1;s47.1" id="SL86"></link>
	<link certainty="1.507397" xtargets="s43.2;s47.2" id="SL87"></link>
	<link certainty="0.667778" xtargets="s43.3;s47.3" id="SL88"></link>
	<link certainty="0.09735" xtargets=";s48.1" id="SL89"></link>
	<link certainty="1.036128" xtargets="s44.1;s49.1" id="SL90"></link>
	<link certainty="1.684298" xtargets="s44.2;s49.2" id="SL91"></link>
	<link certainty="1.04552" xtargets="s44.3;s49.3" id="SL92"></link>
	<link certainty="0.051196" xtargets=";s50.1" id="SL93"></link>
	<link certainty="0.351196" xtargets="s45.1;s51.1" id="SL94"></link>
	<link certainty="1.12353" xtargets="s46.1;s52.1" id="SL96"></link>
	<link certainty="0.728571" xtargets="s47.1;s53.1" id="SL98"></link>
	<link certainty="0.444444" xtargets="s48.1;s54.1" id="SL100"></link>
	<link certainty="0.955943" xtargets="s49.1;s55.1" id="SL102"></link>
	<link certainty="0.223107" xtargets="s49.2 s49.3;s55.2" id="SL103"></link>
	<link certainty="0.44375" xtargets=";s56.1" id="SL104"></link>
	<link certainty="1.521804" xtargets="s50.1;s57.1" id="SL105"></link>
	<link certainty="1.743054" xtargets="s50.2;s57.2" id="SL106"></link>
	<link certainty="2.18318" xtargets="s50.3;s57.3" id="SL107"></link>
	<link certainty="2.49337" xtargets="s50.4;s57.4" id="SL108"></link>
	<link certainty="2.38902" xtargets="s50.5;s57.5" id="SL109"></link>
	<link certainty="1.11383" xtargets="s50.6;s57.6" id="SL110"></link>
	<link certainty="3.128577" xtargets="s51.1;s58.1" id="SL112"></link>
	<link certainty="1.5646" xtargets="s51.2;s58.2" id="SL113"></link>
	<link certainty="3.688213" xtargets="s51.3;s58.3" id="SL114"></link>
	<link certainty="2.76383" xtargets="s51.4;s58.4" id="SL115"></link>
	<link certainty="0.636842" xtargets=";s59.1" id="SL116"></link>
	<link certainty="1.965712" xtargets="s52.1;s60.1" id="SL117"></link>
	<link certainty="2.07887" xtargets="s52.2;s60.2" id="SL118"></link>
	<link certainty="2.20714" xtargets="s52.3;s60.3" id="SL119"></link>
	<link certainty="1.15714" xtargets="s52.4;s60.4" id="SL120"></link>
	<link certainty="1.572885" xtargets="s53.1;s61.1" id="SL122"></link>
	<link certainty="1.43791" xtargets="s53.2;s61.2" id="SL123"></link>
	<link certainty="1.169698" xtargets="s53.3;s61.3" id="SL124"></link>
	<link certainty="1.259158" xtargets="s53.4;s61.4" id="SL125"></link>
	<link certainty="1.546268" xtargets="s53.5;s61.5" id="SL126"></link>
	<link certainty="0.766667" xtargets="s53.6;s61.6" id="SL127"></link>
	<link certainty="0.536008" xtargets=";s62.1" id="SL128"></link>
	<link certainty="1.664133" xtargets="s54.1;s63.1" id="SL129"></link>
	<link certainty="0.828125" xtargets="s54.2;s63.2" id="SL130"></link>
	<link certainty="1.98607" xtargets=";s64.1" id="SL131"></link>
	<link certainty="3.199204" xtargets="s55.1;s65.1" id="SL132"></link>
	<link certainty="0.913134" xtargets="s55.2;s65.2" id="SL133"></link>
	<link certainty="2.24" xtargets=";s66.1" id="SL134"></link>
	<link certainty="2.54" xtargets="s56.1;s67.1" id="SL135"></link>
	<link certainty="1.113602" xtargets="s57.1;s68.1" id="SL137"></link>
	<link certainty="0.736262" xtargets="s57.2;s68.2" id="SL138"></link>
	<link certainty="0.556262" xtargets="s57.3;s68.3" id="SL139"></link>
	<link certainty="1.61879" xtargets=";s69.1" id="SL140"></link>
	<link certainty="1.91879" xtargets="s58.1;s70.1" id="SL141"></link>
	<link certainty="0.374866" xtargets=";s71.1" id="SL142"></link>
	<link certainty="2.402046" xtargets="s59.1;s72.1" id="SL143"></link>
	<link certainty="1.72718" xtargets="s59.2;s72.2" id="SL144"></link>
	<link certainty="0.552926" xtargets=";s73.1" id="SL145"></link>
	<link certainty="1.225899" xtargets="s60.1;s74.1" id="SL146"></link>
	<link certainty="1.406323" xtargets="s60.2;s74.2" id="SL147"></link>
	<link certainty="1.03335" xtargets="s60.3;s74.3" id="SL148"></link>
	<link certainty="0.73964" xtargets=";s75.1" id="SL149"></link>
	<link certainty="1.03964" xtargets="s61.1;s76.1" id="SL150"></link>
	<link certainty="2.265416" xtargets="s62.1;s77.1" id="SL152"></link>
	<link certainty="1.41968" xtargets="s62.2;s77.2" id="SL153"></link>
	<link certainty="4.15763" xtargets="s63.1;s78.1" id="SL155"></link>
	<link certainty="2.19213" xtargets="s63.2;s78.2" id="SL156"></link>
	<link certainty="1.63414" xtargets="s64.1;s79.1" id="SL158"></link>
	<link certainty="0.55984" xtargets="s64.2;s79.2 s79.3" id="SL159"></link>
	<link certainty="5.22" xtargets=";s80.1 s81.1 s81.2" id="SL160"></link>
	<link certainty="6.12" xtargets="s65.1;s82.1" id="SL161"></link>
	<link certainty="-0.0275099999999999" xtargets="s66.1 s66.2 s66.3 s66.4 s66.5 s66.6 s66.7;s82.2" id="SL162"></link>
	<link certainty="0.953234" xtargets="s67.1;s83.1" id="SL164"></link>
	<link certainty="1.885953" xtargets="s68.1;s84.1" id="SL166"></link>
	<link certainty="0.759533" xtargets="s68.2;s84.2" id="SL167"></link>
	<link certainty="2.05007" xtargets="s69.1;s85.1" id="SL169"></link>
	<link certainty="1.589368" xtargets="s69.2;s85.2" id="SL170"></link>
	<link certainty="1.08736" xtargets="s69.3;s85.3" id="SL171"></link>
	<link certainty="0.507032" xtargets="s69.4;s85.4" id="SL172"></link>
	<link certainty="1.984488" xtargets="s70.1;s86.1" id="SL174"></link>
	<link certainty="2.363198" xtargets="s70.2;s86.2" id="SL175"></link>
	<link certainty="3.86863" xtargets="s70.3;s86.3" id="SL176"></link>
	<link certainty="3.133236" xtargets="s70.4;s86.4" id="SL177"></link>
	<link certainty="2.119366" xtargets="s70.5;s86.5" id="SL178"></link>
	<link certainty="1.42738" xtargets="s70.6;s86.6" id="SL179"></link>
	<link certainty="1.57302" xtargets="s71.1;s87.1" id="SL181"></link>
	<link certainty="0.3" xtargets="s71.2;s87.2" id="SL182"></link>
	<link certainty="2.61601" xtargets="s72.1;s88.1" id="SL184"></link>
	<link certainty="1.59319" xtargets="s72.2;s88.2" id="SL185"></link>
	<link certainty="2.625071" xtargets="s73.1 s73.2;s89.1" id="SL187"></link>
	<link certainty="3.193765" xtargets="s73.3;s89.2" id="SL188"></link>
	<link certainty="0.771905" xtargets="s73.4;s89.3" id="SL189"></link>
	<link certainty="1.252554" xtargets="s74.1;s90.1" id="SL191"></link>
	<link certainty="1.620445" xtargets="s74.2;s90.2" id="SL192"></link>
	<link certainty="0.876761" xtargets="s74.3;s90.3" id="SL193"></link>
	<link certainty="1.108696" xtargets="s75.1;s91.1" id="SL195"></link>
	<link certainty="0.821739" xtargets="s75.2;s91.2" id="SL196"></link>
	<link certainty="0.828" xtargets="s76.1;s92.1" id="SL198"></link>
	<link certainty="0.946429" xtargets="s77.1;s93.1" id="SL200"></link>
	<link certainty="0.363971" xtargets=";s94.1" id="SL201"></link>
	<link certainty="1.481662" xtargets="s78.1;s95.1" id="SL202"></link>
	<link certainty="0.817691" xtargets="s78.2;s95.2" id="SL203"></link>
	<link certainty="0.385417" xtargets=";s96.1" id="SL204"></link>
	<link certainty="1.395527" xtargets="s79.1;s97.1" id="SL205"></link>
	<link certainty="0.71011" xtargets="s79.2;s97.2" id="SL206"></link>
	<link certainty="2.065397" xtargets="s80.1;s98.1" id="SL208"></link>
	<link certainty="1.17564" xtargets="s80.2;s98.2" id="SL209"></link>
	<link certainty="1.442324" xtargets="s81.1;s99.1" id="SL211"></link>
	<link certainty="1.723694" xtargets="s81.2;s99.2" id="SL212"></link>
	<link certainty="1.43467" xtargets="s81.3;s99.3" id="SL213"></link>
	<link certainty="0.307317" xtargets="s82.1;s100.1" id="SL215"></link>
	<link certainty="0.711278" xtargets="s83.1;s101.1" id="SL217"></link>
	<link certainty="2.23333" xtargets="s84.1;s102.1" id="SL219"></link>
	<link certainty="1.37167" xtargets="s85.1;s103.1" id="SL221"></link>
	<link certainty="2.33129" xtargets="s86.1;s104.1" id="SL223"></link>
	<link certainty="2.34596" xtargets="s86.2;s104.2" id="SL224"></link>
	<link certainty="1.04333" xtargets="s86.3;s104.3" id="SL225"></link>
	<link certainty="1.12453" xtargets="s87.1;s105.1" id="SL227"></link>
	<link certainty="0.663636" xtargets="s88.1;s106.1" id="SL229"></link>
	<link certainty="-2.4" xtargets=";s107.1 s108.1 s109.1 s110.1 s111.1 s112.1 s113.1 s114.1 s115.1" id="SL230"></link>
	<link certainty="0.3" xtargets="s89.1;s116.1" id="SL231"></link>
	<link certainty="0.473077" xtargets=";s117.1" id="SL232"></link>
	<link certainty="0.773077" xtargets="s90.1;s118.1" id="SL233"></link>
	<link certainty="-0.081818" xtargets=";s119.1" id="SL234"></link>
	<link certainty="0.218182" xtargets="s91.1;s120.1" id="SL235"></link>
	<link certainty="9.3" xtargets="s92.1;s121.1" id="SL237"></link>
	<link certainty="-0.09" xtargets="s93.1;s122.1" id="SL239"></link>
	<link certainty="0.0375" xtargets="s94.1;s123.1" id="SL241"></link>
	<link certainty="0.3" xtargets="s95.1;s124.1" id="SL243"></link>
	<link certainty="0.13125" xtargets="s96.1;s125.1" id="SL245"></link>
	<link certainty="-0.1125" xtargets="s97.1;" id="SL246"></link>
	<link certainty="0.1875" xtargets="s98.1;s126.1" id="SL247"></link>
	<link certainty="-0.081818" xtargets="s99.1;" id="SL248"></link>
	<link certainty="0.218182" xtargets="s100.1;s127.1" id="SL249"></link>
	<link certainty="1.22105" xtargets="s101.1;s128.1" id="SL251"></link>
	<link certainty="0.157895" xtargets="s102.1;s129.1" id="SL253"></link>
	<link certainty="-0.6" xtargets="s103.1;s130.1" id="SL255"></link>
	<link certainty="0.3" xtargets="s104.1;s131.1" id="SL257"></link>
	<link certainty="1.659754" xtargets="s105.1;s132.1" id="SL259"></link>
	<link certainty="0.568914" xtargets="s105.2;s132.2" id="SL260"></link>
	<link certainty="1.900589" xtargets="s106.1;s133.1" id="SL262"></link>
	<link certainty="0.933158" xtargets="s106.2;s133.2" id="SL263"></link>
	<link certainty="0.264935" xtargets="s107.1 s107.2;s134.1" id="SL265"></link>
	<link certainty="1.824008" xtargets="s108.1;s135.1" id="SL267"></link>
	<link certainty="1.348667" xtargets="s108.2;s135.2" id="SL268"></link>
	<link certainty="1.352862" xtargets="s108.3;s135.3" id="SL269"></link>
	<link certainty="0.840275" xtargets="s108.4;s135.4" id="SL270"></link>
	<link certainty="1.590436" xtargets="s109.1;s136.1" id="SL272"></link>
	<link certainty="1.475453" xtargets="s109.2;s136.2" id="SL273"></link>
	<link certainty="1.603343" xtargets="s109.3;s136.3" id="SL274"></link>
	<link certainty="0.898701" xtargets="s109.4;s136.4" id="SL275"></link>
	<link certainty="-0.033377" xtargets="s109.5;s137.1 s138.1 s139.1" id="SL276"></link>
	<link certainty="8.92727" xtargets=";s140.1 s141.1 s142.1" id="SL277"></link>
	<link certainty="9.82727" xtargets="s110.1;s143.1" id="SL278"></link>
	<link certainty="-0.225" xtargets="s111.1;s144.1" id="SL280"></link>
	<link certainty="-0.106173" xtargets="s112.1;s145.1 s145.2 s145.3" id="SL282"></link>
	<link certainty="-0.190385" xtargets="s113.1;s146.1 s146.2" id="SL284"></link>
	<link certainty="0.225" xtargets="s114.1;s147.1" id="SL286"></link>
	<link certainty="-0.092308" xtargets=";s148.1" id="SL288"></link>
	<link certainty="0.207692" xtargets="s115.1;s148.2" id="SL289"></link>
	<link certainty="-0.21" xtargets="s116.1;s149.1" id="SL291"></link>
	<link certainty="0.208567" xtargets="s117.1;s150.1" id="SL293"></link>
	<link certainty="1.272321" xtargets="s117.2;s150.2" id="SL294"></link>
	<link certainty="0.463754" xtargets="s117.3;s150.3" id="SL295"></link>
	<link certainty="-0.3" xtargets="s118.1;s151.1" id="SL297"></link>
	<link certainty="-0.6" xtargets="s118.2;" id="SL298"></link>
	<link certainty="-0.070588" xtargets="s119.1 s119.2;s152.1" id="SL299"></link>
	<link certainty="-0.062963" xtargets="s120.1 s120.2;s152.2" id="SL300"></link>
	<link certainty="-0.066667" xtargets="s121.1;s153.1" id="SL302"></link>
	<link certainty="-0.9" xtargets="s121.2;" id="SL303"></link>
	<link certainty="0.0477270000000001" xtargets="s122.1;s154.1" id="SL304"></link>
	<link certainty="0.647727" xtargets="s122.2;s154.2" id="SL305"></link>
	<link certainty="1.968515" xtargets="s123.1;s155.1" id="SL307"></link>
	<link certainty="2.54157" xtargets="s123.2;s155.2" id="SL308"></link>
	<link certainty="1.41968" xtargets="s123.3;s155.3" id="SL309"></link>
	<link certainty="2.364185" xtargets="s124.1;s156.1" id="SL311"></link>
	<link certainty="1.41968" xtargets="s124.2;s156.2" id="SL312"></link>
	<link certainty="1.125" xtargets="s125.1;s157.1" id="SL314"></link>
	<link certainty="0.55508" xtargets="s126.1;s158.1" id="SL316"></link>
	<link certainty="4.47662" xtargets="s127.1;s159.1" id="SL318"></link>
	<link certainty="1.98883" xtargets="s127.2;s159.2" id="SL319"></link>
	<link certainty="0.584875" xtargets="s128.1;s160.1" id="SL321"></link>
	<link certainty="0.711538" xtargets="s129.1;s161.1" id="SL323"></link>
	<link certainty="1.953846" xtargets="s130.1;s162.1" id="SL325"></link>
	<link certainty="0.253846" xtargets="s130.2;s162.2" id="SL326"></link>
	<link certainty="0.987931" xtargets="s131.1;s163.1" id="SL328"></link>
	<link certainty="0.3055701" xtargets="s132.1;s164.1" id="SL330"></link>
	<link certainty="1.8142241" xtargets="s132.2;s164.2" id="SL331"></link>
	<link certainty="1.7625" xtargets="s132.3;s164.3" id="SL332"></link>
	<link certainty="1.89006" xtargets="s133.1;s165.1" id="SL334"></link>
	<link certainty="0.29542" xtargets="s133.2;s165.2" id="SL335"></link>
	<link certainty="0.275" xtargets="s134.1;s165.3" id="SL336"></link>
	<link certainty="0.864142" xtargets="s135.1;s166.1" id="SL338"></link>
	<link certainty="1.191036" xtargets="s135.2;s166.2" id="SL339"></link>
	<link certainty="0.474586" xtargets="s135.3;s166.3" id="SL340"></link>
	<link certainty="3.464302" xtargets="s136.1;s167.1" id="SL342"></link>
	<link certainty="1.367919" xtargets="s136.2;s167.2" id="SL343"></link>
	<link certainty="2.089417" xtargets="s136.3;s167.3" id="SL344"></link>
	<link certainty="3.40905" xtargets="s136.4;s167.4" id="SL345"></link>
	<link certainty="2.554545" xtargets="s136.5;s167.5" id="SL346"></link>
	<link certainty="0.635971" xtargets="s136.6 s136.7;s167.6" id="SL347"></link>
	<link certainty="0.367766" xtargets="s136.8;s167.7" id="SL348"></link>
	<link certainty="1.738093" xtargets="s137.1;s168.1" id="SL350"></link>
	<link certainty="1.00875" xtargets="s137.2;s168.2" id="SL351"></link>
	<link certainty="1.248455" xtargets="s138.1;s169.1" id="SL353"></link>
	<link certainty="0.472727" xtargets="s138.2;s169.2" id="SL354"></link>
	<link certainty="0.750097" xtargets="s139.1;s170.1" id="SL356"></link>
	<link certainty="1.437376" xtargets="s140.1;s171.1" id="SL358"></link>
	<link certainty="1.07335" xtargets="s140.2;s171.2" id="SL359"></link>
	<link certainty="1.218423" xtargets="s140.3;s171.3" id="SL360"></link>
	<link certainty="1.743144" xtargets="s140.4;s171.4" id="SL361"></link>
	<link certainty="2.16476" xtargets="s140.5;s171.5" id="SL362"></link>
	<link certainty="2.03733" xtargets="s140.6;s171.6" id="SL363"></link>
	<link certainty="1.776683" xtargets="s140.7;s171.7" id="SL364"></link>
	<link certainty="0.806683" xtargets="s140.8;s171.8" id="SL365"></link>
	<link certainty="-0.0160714" xtargets="s140.9;s172.1 s172.2" id="SL366"></link>
	<link certainty="4.15922" xtargets="s141.1;s173.1" id="SL368"></link>
	<link certainty="3.48515" xtargets="s141.2;s173.2" id="SL369"></link>
	<link certainty="1.326875" xtargets="s141.3;s173.3" id="SL370"></link>
	<link certainty="2.531085" xtargets="s141.4 s141.5;s173.4" id="SL371"></link>
	<link certainty="2.84672" xtargets="s141.6;s173.5" id="SL372"></link>
	<link certainty="2.01219" xtargets="s141.7;s173.6" id="SL373"></link>
	<link certainty="1.59506" xtargets="s141.8;s173.7" id="SL374"></link>
	<link certainty="1.089527" xtargets="s142.1;s174.1" id="SL376"></link>
	<link certainty="1.458777" xtargets="s142.2;s174.2" id="SL377"></link>
	<link certainty="0.980182" xtargets="s142.3;s174.3" id="SL378"></link>
	<link certainty="0.3" xtargets="s143.1;s175.1" id="SL380"></link>
	<link certainty="0.709369" xtargets="s144.1;s176.1" id="SL382"></link>
	<link certainty="0.288" xtargets="s144.2;s176.2" id="SL383"></link>
	<link certainty="0.606429" xtargets="s145.1;s177.1" id="SL385"></link>
	<link certainty="1.10299" xtargets="s146.1;s178.1" id="SL387"></link>
	<link certainty="1.15385" xtargets="s147.1;" id="SL388"></link>
	<link certainty="1.45385" xtargets="s148.1;s179.1" id="SL389"></link>
	<link certainty="-0.425" xtargets="s149.1;s180.1" id="SL391"></link>
	<link certainty="0.96" xtargets="s150.1;s181.1" id="SL393"></link>
	<link certainty="1.433726" xtargets="s151.1;s182.1" id="SL395"></link>
	<link certainty="0.927232" xtargets="s151.2;s182.2" id="SL396"></link>
	<link certainty="1.297376" xtargets="s152.1;s183.1" id="SL398"></link>
	<link certainty="0.436765" xtargets="s152.2 s152.3;s183.2" id="SL399"></link>
	<link certainty="3.550634" xtargets="s153.1;s184.1" id="SL401"></link>
	<link certainty="0.842754" xtargets="s153.2;s184.2" id="SL402"></link>
	<link certainty="0.796512" xtargets="s154.1;s185.1" id="SL404"></link>
	<link certainty="1.01599" xtargets="s155.1;s186.1" id="SL406"></link>
	<link certainty="0.115964" xtargets="s156.1 s156.2;s187.1" id="SL408"></link>
	<link certainty="0.292021" xtargets="s157.1 s157.2;s188.1" id="SL410"></link>
	<link certainty="0.315333" xtargets="s158.1 s158.2;s189.1" id="SL412"></link>
	<link certainty="0.206739" xtargets="s159.1 s159.2;s190.1" id="SL414"></link>
	<link certainty="4.61413" xtargets="s160.1 s160.2;" id="SL415"></link>
	<link certainty="4.91413" xtargets="s161.1;s191.1" id="SL416"></link>
	<link certainty="4.48699" xtargets="s161.2;s192.1" id="SL417"></link>
	<link certainty="1.01129" xtargets="s162.1;s193.1" id="SL419"></link>
	<link certainty="1.8" xtargets="s163.1;s194.1" id="SL421"></link>
	<link certainty="0.785417" xtargets="s164.1;s195.1" id="SL423"></link>
	<link certainty="1.329308" xtargets="s165.1;s196.1" id="SL425"></link>
	<link certainty="1.521372" xtargets="s165.2 s165.3;s196.2" id="SL426"></link>
	<link certainty="0.835612" xtargets="s165.4;s196.3" id="SL427"></link>
	<link certainty="0.470297" xtargets="s166.1;s197.1" id="SL429"></link>
	<link certainty="0" xtargets=";s198.1" id="SL430"></link>
	<link certainty="0.3" xtargets="s167.1;s199.1" id="SL431"></link>
	<link certainty="3.155938" xtargets="s168.1;s200.1" id="SL433"></link>
	<link certainty="0.977118" xtargets="s168.2;s200.2" id="SL434"></link>
	<link certainty="0.824658" xtargets="s169.1 s169.2;s200.3" id="SL435"></link>
	<link certainty="1.157222" xtargets="s169.3;s200.4" id="SL436"></link>
	<link certainty="4.770134" xtargets="s169.4;s200.5" id="SL437"></link>
	<link certainty="4.26757" xtargets="s169.5;s200.6" id="SL438"></link>
	<link certainty="-0.115385" xtargets=";s201.1" id="SL439"></link>
	<link certainty="0.184615" xtargets="s170.1;s202.1" id="SL440"></link>
	<link certainty="2.75325" xtargets="s171.1;s203.1" id="SL442"></link>
	<link certainty="0.150769" xtargets=";s204.1" id="SL443"></link>
	<link certainty="1.114453" xtargets="s172.1;s205.1" id="SL444"></link>
	<link certainty="2.262334" xtargets="s172.2;s205.2" id="SL445"></link>
	<link certainty="2.293075" xtargets="s172.3;s205.3" id="SL446"></link>
	<link certainty="1.766985" xtargets="s172.4;s205.4" id="SL447"></link>
	<link certainty="1.07256" xtargets="s172.5;s205.5" id="SL448"></link>
	<link certainty="1.407167" xtargets="s173.1;s206.1" id="SL450"></link>
	<link certainty="0.856579" xtargets="s173.2;s206.2" id="SL451"></link>
	<link certainty="2.03825" xtargets="s174.1;s207.1" id="SL453"></link>
	<link certainty="1.32377" xtargets="s174.2;s207.2" id="SL454"></link>
	<link certainty="1.91946" xtargets=";s208.1" id="SL455"></link>
	<link certainty="3.154362" xtargets="s175.1;s209.1" id="SL456"></link>
	<link certainty="3.224462" xtargets="s175.2;s209.2" id="SL457"></link>
	<link certainty="2.28956" xtargets="s175.3;s209.3" id="SL458"></link>
	<link certainty="2.28555" xtargets=";s210.1" id="SL459"></link>
	<link certainty="2.58555" xtargets="s176.1;s211.1" id="SL460"></link>
	<link certainty="0.74548" xtargets=";s212.1" id="SL461"></link>
	<link certainty="1.509116" xtargets="s177.1;s213.1" id="SL462"></link>
	<link certainty="0.463636" xtargets="s177.2;s213.2" id="SL463"></link>
	<link certainty="0.369412" xtargets=";s214.1" id="SL464"></link>
	<link certainty="1.090633" xtargets="s178.1;s215.1" id="SL465"></link>
	<link certainty="0.421221" xtargets="s178.2;s215.2" id="SL466"></link>
	<link certainty="0" xtargets=";s216.1" id="SL467"></link>
	<link certainty="0.3" xtargets="s179.1;s217.1" id="SL468"></link>
	<link certainty="2.79748" xtargets="s180.1;s218.1" id="SL470"></link>
	<link certainty="2.279401" xtargets="s180.2 s180.3;s218.2" id="SL471"></link>
	<link certainty="0.973881" xtargets="s180.4;s218.3" id="SL472"></link>
	<link certainty="0.850988" xtargets="s181.1;s219.1" id="SL474"></link>
	<link certainty="0.959772" xtargets="s181.2;s219.2" id="SL475"></link>
	<link certainty="2.802993" xtargets="s181.3;s219.3" id="SL476"></link>
	<link certainty="2.12583" xtargets="s181.4;s219.4" id="SL477"></link>
	<link certainty="2.579718" xtargets="s182.1;s220.1" id="SL479"></link>
	<link certainty="3.32074" xtargets="s182.2;s220.2" id="SL480"></link>
	<link certainty="1.13333" xtargets="s182.3;s220.3" id="SL481"></link>
	<link certainty="-0.194118" xtargets=";s221.1" id="SL482"></link>
	<link certainty="0.405882" xtargets="s183.1;s222.1" id="SL483"></link>
	<link certainty="0.918243" xtargets="s183.2;s222.2" id="SL484"></link>
	<link certainty="0.880743" xtargets="s183.3;s222.3" id="SL485"></link>
	<link certainty="4.72614" xtargets="s183.4;s222.4" id="SL486"></link>
	<link certainty="4.46364" xtargets="s183.5;s222.5" id="SL487"></link>
	<link certainty="0.175833" xtargets=";s223.1" id="SL488"></link>
	<link certainty="1.467296" xtargets="s184.1;s224.1" id="SL489"></link>
	<link certainty="0.991463" xtargets="s184.2;s224.2" id="SL490"></link>
	<link certainty="0.509248" xtargets=";s225.1" id="SL491"></link>
	<link certainty="1.701556" xtargets="s185.1;s226.1" id="SL492"></link>
	<link certainty="1.200135" xtargets="s185.2;s226.2" id="SL493"></link>
	<link certainty="0.307827" xtargets="s185.3 s185.4;s226.3" id="SL494"></link>
	<link certainty="0.78" xtargets="s186.1;s227.1" id="SL496"></link>
	<link certainty="1.322008" xtargets="s187.1;s228.1" id="SL498"></link>
	<link certainty="0.306038" xtargets="s187.2 s187.3;s228.2" id="SL499"></link>
	<link certainty="0.230769" xtargets="s188.1;s229.1" id="SL501"></link>
	<link certainty="1.295385" xtargets="s189.1;s230.1" id="SL503"></link>
	<link certainty="0.723854" xtargets="s189.2;s230.2" id="SL504"></link>
	<link certainty="0.718855" xtargets="s189.3;s230.3" id="SL505"></link>
	<link certainty="1.19684" xtargets="s189.4;s230.4" id="SL506"></link>
	<link certainty="0.601318" xtargets="s189.5;s230.5" id="SL507"></link>
	<link certainty="4.04211" xtargets="s190.1;s231.1" id="SL509"></link>
	<link certainty="3.14811" xtargets="s190.2;s231.2" id="SL510"></link>
	<link certainty="1.00208" xtargets="s191.1 s191.2;s231.3" id="SL511"></link>
	<link certainty="2.4466" xtargets="s191.3;s231.4" id="SL512"></link>
	<link certainty="2.17785" xtargets="s191.4;s231.5" id="SL513"></link>
	<link certainty="2.11752" xtargets="s192.1;s232.1" id="SL515"></link>
	<link certainty="1.03333" xtargets="s192.2;s232.2" id="SL516"></link>
	<link certainty="0.27" xtargets="s193.1;s233.1" id="SL518"></link>
	<link certainty="0.421809" xtargets="s194.1;s234.1" id="SL520"></link>
	<link certainty="2.06087" xtargets="s195.1;s235.1" id="SL522"></link>
	<link certainty="0.26087" xtargets="s195.2;s235.2" id="SL523"></link>
	<link certainty="0.705" xtargets="s196.1;s236.1" id="SL525"></link>
	<link certainty="0.229306" xtargets="s197.1;s237.1 s237.2" id="SL527"></link>
	<link certainty="2.40083" xtargets="s198.1;s238.1 s238.2" id="SL529"></link>
	<link certainty="1.27143" xtargets="s199.1;s239.1" id="SL531"></link>
	<link certainty="0.26" xtargets="s200.1;s240.1" id="SL533"></link>
	<link certainty="0.819231" xtargets="s201.1;s241.1" id="SL535"></link>
	<link certainty="9.3" xtargets="s202.1;s242.1" id="SL537"></link>
	<link certainty="1.12187" xtargets="s203.1;s243.1" id="SL539"></link>
	<link certainty="0.842857" xtargets="s204.1;s244.1" id="SL541"></link>
	<link certainty="0.709821" xtargets="s205.1;s245.1" id="SL543"></link>
	<link certainty="2.85925" xtargets="s206.1;s246.1" id="SL545"></link>
	<link certainty="-0.1" xtargets="s207.1;s247.1" id="SL547"></link>
	<link certainty="1.14545" xtargets="s208.1;s248.1" id="SL549"></link>
	<link certainty="0.208696" xtargets="s209.1;s249.1" id="SL551"></link>
	<link certainty="1.765" xtargets="s210.1;s250.1" id="SL553"></link>
	<link certainty="0.165" xtargets="s210.2;s250.2" id="SL554"></link>
	<link certainty="4.26897" xtargets="s211.1;s251.1" id="SL556"></link>
	<link certainty="1.92" xtargets="s212.1;s252.1" id="SL558"></link>
	<link certainty="0.12" xtargets="s212.2;s252.2" id="SL559"></link>
	<link certainty="0.3" xtargets="s213.1;s253.1" id="SL561"></link>
	<link certainty="2.82059" xtargets="s214.1;s254.1" id="SL563"></link>
	<link certainty="1.02059" xtargets="s214.2;s254.2" id="SL564"></link>
	<link certainty="0.466667" xtargets="s215.1 s215.2;s255.1" id="SL566"></link>
	<link certainty="1.29" xtargets="s216.1;s256.1" id="SL568"></link>
	<link certainty="0.99" xtargets="s216.2;s256.2" id="SL569"></link>
	<link certainty="1.02" xtargets="s217.1;s257.1" id="SL571"></link>
	<link certainty="2.395" xtargets="s218.1;s258.1" id="SL573"></link>
	<link certainty="0.595" xtargets="s218.2;s258.2" id="SL574"></link>
	<link certainty="2.513158" xtargets="s219.1;s259.1" id="SL576"></link>
	<link certainty="0.713158" xtargets="s219.2;s259.2" id="SL577"></link>
	<link certainty="1.895" xtargets="s220.1;s260.1" id="SL579"></link>
	<link certainty="0.595" xtargets="s220.2;s260.2" id="SL580"></link>
	<link certainty="0.769183" xtargets="s221.1;s261.1" id="SL582"></link>
	<link certainty="2.19906" xtargets="s222.1 s222.2;s262.1" id="SL584"></link>
	<link certainty="2.75" xtargets="s223.1;s263.1" id="SL586"></link>
	<link certainty="6.68723" xtargets="s224.1;s264.1" id="SL588"></link>
	<link certainty="5.38723" xtargets="s224.2;s264.2" id="SL589"></link>
	<link certainty="0.725448" xtargets="s225.1;s265.1" id="SL591"></link>
	<link certainty="2.513158" xtargets="s226.1;s266.1" id="SL593"></link>
	<link certainty="0.713158" xtargets="s226.2;s266.2" id="SL594"></link>
	<link certainty="0.568539" xtargets="s227.1;s267.1" id="SL596"></link>
	<link certainty="0.26087" xtargets="s228.1;s268.1" id="SL598"></link>
	<link certainty="0.718165" xtargets="s229.1;s269.1" id="SL600"></link>
	<link certainty="1.48689" xtargets=";s270.1" id="SL601"></link>
	<link certainty="1.78689" xtargets="s230.1;s271.1" id="SL602"></link>
	<link certainty="0.717135" xtargets="s231.1;s272.1" id="SL604"></link>
	<link certainty="1.67106" xtargets="s232.1;s273.1" id="SL606"></link>
	<link certainty="0.868111" xtargets="s233.1;s274.1" id="SL608"></link>
	<link certainty="1.02273" xtargets="s234.1;s275.1" id="SL610"></link>
	<link certainty="0.244444" xtargets="s235.1;s276.1" id="SL612"></link>
	<link certainty="1.48" xtargets="s236.1;s277.1" id="SL614"></link>
	<link certainty="0.18" xtargets="s236.2;s277.2" id="SL615"></link>
	<link certainty="0.248571" xtargets="s237.1;s278.1" id="SL617"></link>
	<link certainty="-0.0428571" xtargets="s238.1;s279.1" id="SL619"></link>
	<link certainty="2.82692" xtargets="s239.1;s280.1" id="SL621"></link>
	<link certainty="1.02692" xtargets="s239.2;s280.2" id="SL622"></link>
	<link certainty="1.75455" xtargets="s240.1;s281.1" id="SL624"></link>
	<link certainty="1.14514" xtargets="s241.1;s282.1" id="SL626"></link>
	<link certainty="1.581818" xtargets="s242.1;s283.1" id="SL628"></link>
	<link certainty="-0.218182" xtargets="s242.2;s283.2" id="SL629"></link>
	<link certainty="3.675" xtargets="s243.1;s284.1" id="SL631"></link>
	<link certainty="2.029412" xtargets="s244.1;s285.1" id="SL633"></link>
	<link certainty="0.229412" xtargets="s244.2;s285.2" id="SL634"></link>
	<link certainty="2.053846" xtargets="s245.1;s286.1" id="SL636"></link>
	<link certainty="0.253846" xtargets="s245.2;s286.2" id="SL637"></link>
	<link certainty="4.65599" xtargets="s246.1;s287.1" id="SL639"></link>
	<link certainty="2.488571" xtargets="s247.1;s288.1" id="SL641"></link>
	<link certainty="0.688571" xtargets="s247.2;s288.2" id="SL642"></link>
	<link certainty="1.216" xtargets="s248.1;s289.1" id="SL644"></link>
	<link certainty="0.966" xtargets="s248.2;s289.2" id="SL645"></link>
	<link certainty="2.510053" xtargets="s249.1;s290.1" id="SL647"></link>
	<link certainty="0.710053" xtargets="s249.2;s290.2" id="SL648"></link>
	<link certainty="0.210811" xtargets="s250.1;s291.1" id="SL650"></link>
	<link certainty="2.074286" xtargets="s251.1;s292.1" id="SL652"></link>
	<link certainty="0.274286" xtargets="s251.2;s292.2" id="SL653"></link>
	<link certainty="2.045455" xtargets="s252.1;s293.1" id="SL655"></link>
	<link certainty="0.245455" xtargets="s252.2;s293.2" id="SL656"></link>
	<link certainty="2.025" xtargets="s253.1;s294.1" id="SL658"></link>
	<link certainty="1.8" xtargets="s253.2;s294.2" id="SL659"></link>
	<link certainty="1.576" xtargets="s254.1;s295.1" id="SL661"></link>
	<link certainty="0.276" xtargets="s254.2;s295.2" id="SL662"></link>
	<link certainty="0.771795" xtargets="s255.1;s296.1" id="SL664"></link>
	<link certainty="0.471795" xtargets="s255.2;s296.2" id="SL665"></link>
	<link certainty="1.45714" xtargets="s256.1;s297.1" id="SL667"></link>
	<link certainty="1.15714" xtargets="s256.2;s297.2" id="SL668"></link>
	<link certainty="4.26897" xtargets="s257.1;s298.1" id="SL670"></link>
	<link certainty="0.42" xtargets="s258.1;s299.1" id="SL672"></link>
	<link certainty="0.12" xtargets="s258.2;s299.2" id="SL673"></link>
	<link certainty="2.2038" xtargets="s259.1;s300.1" id="SL675"></link>
	<link certainty="0.425" xtargets="s260.1;s301.1" id="SL677"></link>
	<link certainty="0.125" xtargets="s260.2;s301.2" id="SL678"></link>
	<link certainty="1.9125" xtargets="s261.1;s302.1" id="SL680"></link>
	<link certainty="1.8" xtargets="s261.2;s302.2" id="SL681"></link>
	<link certainty="-0.3" xtargets=";s303.1 s303.2 s304.1" id="SL682"></link>
	<link certainty="0.583333" xtargets="s262.1;s305.1" id="SL683"></link>
	<link certainty="0.283333" xtargets="s262.2;s305.2" id="SL684"></link>
	<link certainty="-0.006" xtargets="s263.1;s306.1 s306.2" id="SL686"></link>
	<link certainty="4.6" xtargets="s264.1 s264.2;s307.1" id="SL688"></link>
	<link certainty="-0.344681" xtargets="s265.1 s265.2 s266.1;" id="SL689"></link>
	<link certainty="0.255319" xtargets="s267.1;s308.1" id="SL690"></link>
	<link certainty="0.0375" xtargets="s268.1;s309.1" id="SL692"></link>
	<link certainty="2.82692" xtargets="s269.1;s310.1" id="SL694"></link>
	<link certainty="1.02692" xtargets="s269.2;s310.2" id="SL695"></link>
	<link certainty="1.73333" xtargets="s270.1;s311.1" id="SL697"></link>
	<link certainty="1.5784" xtargets="s271.1;s312.1" id="SL699"></link>
	<link certainty="3.28333" xtargets="s272.1;s313.1" id="SL701"></link>
	<link certainty="1.48333" xtargets="s272.2;s313.2" id="SL702"></link>
	<link certainty="1.5" xtargets="s273.1;s314.1" id="SL704"></link>
	<link certainty="2.045455" xtargets="s274.1;s315.1" id="SL706"></link>
	<link certainty="0.245455" xtargets="s274.2;s315.2" id="SL707"></link>
	<link certainty="2.04" xtargets="s275.1;s316.1" id="SL709"></link>
	<link certainty="1.8" xtargets="s275.2;s316.2" id="SL710"></link>
	<link certainty="1.925" xtargets="s276.1;s317.1" id="SL712"></link>
	<link certainty="0.125" xtargets="s276.2;s317.2" id="SL713"></link>
	<link certainty="1.8428571" xtargets="s277.1;s318.1" id="SL715"></link>
	<link certainty="1.8" xtargets="s277.2;s318.2" id="SL716"></link>
	<link certainty="1.84" xtargets="s278.1;s319.1" id="SL718"></link>
	<link certainty="0.04" xtargets="s278.2;s319.2" id="SL719"></link>
	<link certainty="2.68508" xtargets="s279.1;s320.1" id="SL721"></link>
	<link certainty="1.58" xtargets="s280.1;s321.1" id="SL723"></link>
	<link certainty="0.28" xtargets="s280.2;s321.2" id="SL724"></link>
	<link certainty="-0.1" xtargets="s281.1;s322.1" id="SL726"></link>
	<link certainty="5.01364" xtargets="s281.2 s282.1;s322.2" id="SL727"></link>
	<link certainty="1.78235" xtargets="s283.1;s323.1" id="SL729"></link>
	<link certainty="0.338095" xtargets="s284.1;s324.1" id="SL731"></link>
	<link certainty="1.09067" xtargets="s285.1;s325.1" id="SL733"></link>
	<link certainty="0.024" xtargets="s285.2;s325.2" id="SL734"></link>
	<link certainty="1.22632" xtargets="s286.1;s326.1" id="SL736"></link>
	<link certainty="0.4548441" xtargets="s287.1;s327.1" id="SL738"></link>
	<link certainty="-0.0521739" xtargets="s287.2;s327.2 s327.3" id="SL739"></link>
	<link certainty="0.264706" xtargets="s288.1;s328.1" id="SL741"></link>
	<link certainty="1.42692" xtargets="s289.1;s329.1" id="SL743"></link>
	<link certainty="0.701471" xtargets="s290.1;s330.1" id="SL745"></link>
	<link certainty="2.36" xtargets="s291.1;s331.1" id="SL747"></link>
	<link certainty="2.65" xtargets="s291.2;s331.2" id="SL748"></link>
	<link certainty="0.8206667" xtargets="s291.3;s331.3" id="SL749"></link>
	<link certainty="0.6706667" xtargets="s291.4 s291.5 s291.6;s331.4" id="SL750"></link>
	<link certainty="0.7431373" xtargets="s291.7;s331.5" id="SL751"></link>
	<link certainty="-0.2568627" xtargets="s291.8 s291.9 s291.10;s331.6" id="SL752"></link>
	<link certainty="-0.031579" xtargets="s291.11 s291.12 s291.13;s331.7" id="SL753"></link>
	<link certainty="2.329412" xtargets="s292.1;s332.1" id="SL755"></link>
	<link certainty="0.529412" xtargets="s292.2;s332.2" id="SL756"></link>
	<link certainty="3.529593" xtargets="s293.1;s333.1" id="SL758"></link>
	<link certainty="0.232653" xtargets="s293.2;s333.2" id="SL759"></link>
	<link certainty="0.552261" xtargets="s294.1;s334.1" id="SL761"></link>
	<link certainty="2.36087" xtargets="s295.1;s335.1" id="SL763"></link>
	<link certainty="0.56087" xtargets="s295.2;s335.2" id="SL764"></link>
	<link certainty="1.06" xtargets="s296.1;s336.1" id="SL766"></link>
	<link certainty="1.41786" xtargets="s297.1;s337.1" id="SL768"></link>
	<link certainty="0.683333" xtargets="s298.1;s338.1" id="SL770"></link>
	<link certainty="0.45" xtargets="s299.1;s339.1" id="SL772"></link>
	<link certainty="0.680519" xtargets="s300.1;s340.1" id="SL774"></link>
	<link certainty="0.221739" xtargets="s301.1;s341.1" id="SL776"></link>
	<link certainty="0.5" xtargets="s302.1;s342.1" id="SL778"></link>
	<link certainty="0.831157" xtargets="s303.1;s343.1" id="SL780"></link>
	<link certainty="1.28462" xtargets="s304.1;s344.1" id="SL782"></link>
	<link certainty="-0.518182" xtargets="s305.1;s345.1" id="SL784"></link>
	<link certainty="1.01129" xtargets="s306.1;s346.1" id="SL786"></link>
	<link certainty="1.16047" xtargets="s307.1;s347.1" id="SL788"></link>
	<link certainty="0.14" xtargets="s308.1;s348.1 s348.2" id="SL790"></link>
	<link certainty="0.12607" xtargets="s309.1 s309.2;s349.1" id="SL792"></link>
	<link certainty="1.15882" xtargets="s310.1;s350.1" id="SL794"></link>
	<link certainty="0.125" xtargets="s311.1;s351.1 s351.2" id="SL796"></link>
	<link certainty="0.502597" xtargets="s312.1;s352.1" id="SL798"></link>
	<link certainty="-0.6" xtargets="s313.1;s353.1" id="SL800"></link>
	<link certainty="1.05" xtargets="s314.1;s354.1" id="SL802"></link>
	<link certainty="0.366667" xtargets=";s355.1" id="SL803"></link>
	<link certainty="0.666667" xtargets="s315.1;s356.1" id="SL804"></link>
	<link certainty="0.670972" xtargets="s316.1;s357.1" id="SL806"></link>
	<link certainty="0.678333" xtargets="s317.1;s358.1" id="SL808"></link>
	<link certainty="0.182143" xtargets="s317.2;s358.2" id="SL809"></link>
	<link certainty="-0.012766" xtargets="s318.1;s359.1" id="SL811"></link>
	<link certainty="2.77779" xtargets="s319.1;s360.1" id="SL813"></link>
	<link certainty="1.10675" xtargets="s320.1;s361.1" id="SL815"></link>
	<link certainty="1.38355" xtargets="s321.1;s362.1" id="SL817"></link>
	<link certainty="1.73651" xtargets="s321.2;s362.2" id="SL818"></link>
	<link certainty="0.898415" xtargets="s321.3;s362.3" id="SL819"></link>
	<link certainty="0.597072" xtargets="s322.1;" id="SL821"></link>
	<link certainty="1.385799" xtargets="s322.2;s363.1" id="SL822"></link>
	<link certainty="1.165043" xtargets="s322.3;s363.2" id="SL823"></link>
	<link certainty="0.676316" xtargets="s322.4;s363.3" id="SL824"></link>
	<link certainty="0.0525714" xtargets="s323.1;s364.1" id="SL826"></link>
	<link certainty="0.0285714" xtargets="s323.2;s364.2" id="SL827"></link>
	<link certainty="3.15789" xtargets="s324.1;s365.1" id="SL829"></link>
	<link certainty="1.35789" xtargets="s324.2;s365.2" id="SL830"></link>
	<link certainty="2" xtargets="s325.1;s366.1" id="SL832"></link>
	<link certainty="2.04" xtargets="s325.2;s366.2" id="SL833"></link>
	<link certainty="1.692291" xtargets="s325.3;s366.3" id="SL834"></link>
	<link certainty="0.852291" xtargets="s325.4;s366.4" id="SL835"></link>
	<link certainty="0.798701" xtargets="s326.1;s367.1" id="SL837"></link>
	<link certainty="0.960073" xtargets="s327.1;s368.1" id="SL839"></link>
	<link certainty="0.828008" xtargets="s328.1;s369.1" id="SL841"></link>
	<link certainty="3.34067" xtargets="s329.1;s370.1" id="SL843"></link>
	<link certainty="1.30983" xtargets="s329.2;s370.2" id="SL844"></link>
	<link certainty="2.169006" xtargets="s330.1;s371.1" id="SL846"></link>
	<link certainty="0.784746" xtargets="s330.2;s371.2" id="SL847"></link>
	<link certainty="1.311475" xtargets="s331.1;s372.1" id="SL849"></link>
	<link certainty="1.444119" xtargets="s331.2;s372.2" id="SL850"></link>
	<link certainty="0.837452" xtargets="s331.3;s372.3" id="SL851"></link>
	<link certainty="1.99733" xtargets="s332.1;s373.1" id="SL853"></link>
	<link certainty="1.09733" xtargets="s332.2;s373.2" id="SL854"></link>
	<link certainty="1.443507" xtargets="s333.1;s374.1" id="SL856"></link>
	<link certainty="1.658774" xtargets="s333.2;s374.2" id="SL857"></link>
	<link certainty="1.400981" xtargets="s333.3;s374.3" id="SL858"></link>
	<link certainty="0.328571" xtargets="s333.4;s374.4" id="SL859"></link>
	<link certainty="0.937185" xtargets="s334.1;s375.1" id="SL861"></link>
	<link certainty="0.38169" xtargets="s334.2;s375.2" id="SL862"></link>
	<link certainty="1.2994" xtargets="s335.1;s376.1" id="SL864"></link>
	<link certainty="1.89" xtargets="s336.1;s377.1" id="SL866"></link>
	<link certainty="0.09" xtargets="s336.2;s377.2" id="SL867"></link>
	<link certainty="0.558498" xtargets="s337.1;s378.1" id="SL869"></link>
	<link certainty="0.914984" xtargets="s338.1;s379.1" id="SL871"></link>
	<link certainty="1.000352" xtargets="s339.1;s380.1" id="SL873"></link>
	<link certainty="1.077901" xtargets="s339.2;s380.2" id="SL874"></link>
	<link certainty="0.717364" xtargets="s339.3;s380.3" id="SL875"></link>
	<link certainty="1.21371" xtargets="s340.1;s381.1" id="SL877"></link>
	<link certainty="0.61371" xtargets="s340.2;s381.2" id="SL878"></link>
	<link certainty="4.71886" xtargets="s341.1;s382.1" id="SL880"></link>
	<link certainty="1.12353" xtargets="s342.1;s383.1" id="SL882"></link>
	<link certainty="1.275" xtargets="s343.1;s384.1" id="SL884"></link>
	<link certainty="1.03" xtargets="s344.1;s385.1" id="SL886"></link>
	<link certainty="1.16" xtargets="s345.1;s386.1" id="SL888"></link>
	<link certainty="1.28125" xtargets="s346.1;s387.1" id="SL890"></link>
	<link certainty="1.27" xtargets="s347.1;s388.1" id="SL892"></link>
	<link certainty="1.27273" xtargets="s348.1;s389.1" id="SL894"></link>
	<link certainty="0.364286" xtargets="s349.1;s390.1" id="SL896"></link>
	<link certainty="1.69481" xtargets=";s391.1" id="SL897"></link>
	<link certainty="1.99481" xtargets="s350.1;s392.1" id="SL898"></link>
	<link certainty="1.27273" xtargets="s351.1;s393.1" id="SL900"></link>
	<link certainty="1.175" xtargets="s352.1;s394.1" id="SL902"></link>
	<link certainty="4.62939" xtargets=";s395.1" id="SL903"></link>
	<link certainty="4.92939" xtargets="s353.1;s396.1" id="SL904"></link>
	<link certainty="0.743478" xtargets="s354.1;s397.1" id="SL906"></link>
	<link certainty="1.36667" xtargets="s355.1;s398.1" id="SL908"></link>
	<link certainty="1.09211" xtargets="s356.1;s399.1" id="SL910"></link>
	<link certainty="0.2" xtargets="s357.1;s400.1" id="SL912"></link>
	<link certainty="1.19091" xtargets="s358.1;s401.1" id="SL914"></link>
	<link certainty="1.5" xtargets="s359.1;" id="SL915"></link>
	<link certainty="3.15" xtargets="s360.1;s402.1" id="SL916"></link>
	<link certainty="1.35" xtargets="s360.2;s402.2" id="SL917"></link>
	<link certainty="0.210811" xtargets="s361.1;s403.1" id="SL919"></link>
	<link certainty="0.289202" xtargets="s362.1;s404.1" id="SL921"></link>
	<link certainty="0.82381" xtargets="s363.1;s405.1" id="SL923"></link>
	<link certainty="0.891425" xtargets="s364.1;s406.1" id="SL925"></link>
	<link certainty="0.652198" xtargets="s364.2;s406.2" id="SL926"></link>
	<link certainty="0.271429" xtargets="s364.3;s406.3" id="SL927"></link>
	<link certainty="1.868421" xtargets="s365.1;s407.1" id="SL929"></link>
	<link certainty="0.268421" xtargets="s365.2;s407.2" id="SL930"></link>
	<link certainty="3.29189" xtargets="s366.1;s408.1" id="SL932"></link>
	<link certainty="0.54" xtargets="s366.2;s409.1" id="SL933"></link>
	<link certainty="5.30341" xtargets="s367.1;s410.1" id="SL935"></link>
	<link certainty="3.01697" xtargets="s367.2;s410.2" id="SL936"></link>
	<link certainty="3.825669" xtargets="s368.1;s411.1" id="SL938"></link>
	<link certainty="3.54306" xtargets="s368.2;s411.2" id="SL939"></link>
	<link certainty="2.23327" xtargets="s369.1;s412.1" id="SL941"></link>
	<link certainty="5.58983" xtargets="s369.2;s412.2" id="SL942"></link>
	<link certainty="3.60656" xtargets="s369.3;s412.3" id="SL943"></link>
	<link certainty="3.67008" xtargets="s370.1;s412.4" id="SL944"></link>
	<link certainty="0.65177" xtargets="s371.1;s413.1" id="SL946"></link>
	<link certainty="3.87143" xtargets="s372.1;s414.1" id="SL948"></link>
	<link certainty="3.87143" xtargets="s373.1;s415.1" id="SL950"></link>
	<link certainty="3.65217" xtargets="s374.1;" id="SL951"></link>
	<link certainty="3.95217" xtargets="s375.1;s416.1" id="SL952"></link>
	<link certainty="4.01429" xtargets="s376.1;s417.1" id="SL954"></link>
	<link certainty="8.7" xtargets="s377.1;s418.1" id="SL956"></link>
	<link certainty="6.3" xtargets="s377.2;s418.2" id="SL957"></link>
	<link certainty="5.14615" xtargets="s378.1;s419.1" id="SL959"></link>
	<link certainty="4.15714" xtargets="s379.1;s420.1" id="SL961"></link>
	<link certainty="7.50909" xtargets="s380.1;s421.1" id="SL963"></link>
	<link certainty="5.20909" xtargets="s380.2;s421.2" id="SL964"></link>
	<link certainty="4.8" xtargets="s381.1;s422.1" id="SL966"></link>
	<link certainty="4.15714" xtargets="s382.1;s423.1" id="SL968"></link>
	<link certainty="2.69562" xtargets="s383.1;s424.1" id="SL970"></link>
	<link certainty="7.15909" xtargets="s384.1;s425.1" id="SL972"></link>
	<link certainty="5.20909" xtargets="s384.2;s425.2" id="SL973"></link>
	<link certainty="8.87472" xtargets="s385.1;s426.1" id="SL975"></link>
	<link certainty="6.72857" xtargets="s385.2;s426.2" id="SL976"></link>
	<link certainty="3.98182" xtargets="s386.1;s427.1" id="SL978"></link>
	<link certainty="6.9738" xtargets="s387.1;s428.1" id="SL980"></link>
	<link certainty="5.20909" xtargets="s387.2;s428.2" id="SL981"></link>
	<link certainty="4.6125" xtargets="s388.1;s429.1" id="SL983"></link>
	<link certainty="5.14615" xtargets="s389.1;s430.1" id="SL985"></link>
	<link certainty="9.6" xtargets="s390.1;s431.1" id="SL987"></link>
	<link certainty="7.3" xtargets="s390.2;s431.2" id="SL988"></link>
	<link certainty="5.14615" xtargets="s391.1;s432.1" id="SL990"></link>
	<link certainty="8.36667" xtargets="s392.1;s433.1" id="SL992"></link>
	<link certainty="5.96667" xtargets="s392.2;s433.2" id="SL993"></link>
	<link certainty="8.88235" xtargets="s393.1;s434.1" id="SL995"></link>
	<link certainty="6.78235" xtargets="s393.2;s434.2" id="SL996"></link>
	<link certainty="8.475" xtargets="s394.1;s435.1" id="SL998"></link>
	<link certainty="6.3" xtargets="s394.2;s435.2" id="SL999"></link>
	<link certainty="5.14615" xtargets="s395.1;s436.1" id="SL1001"></link>
	<link certainty="4.68462" xtargets="s396.1;s437.1" id="SL1003"></link>
	<link certainty="4.08261" xtargets="s397.1;s438.1" id="SL1005"></link>
	<link certainty="4.15714" xtargets="s398.1;s439.1" id="SL1007"></link>
	<link certainty="2.97576" xtargets="s399.1;s440.1" id="SL1009"></link>
	<link certainty="5.01429" xtargets="s400.1;s441.1" id="SL1011"></link>
	<link certainty="4.8" xtargets="s401.1;s442.1" id="SL1013"></link>
	<link certainty="1.00286" xtargets="s402.1;s443.1" id="SL1015"></link>
	<link certainty="0.864338" xtargets="s403.1;s444.1" id="SL1017"></link>
	<link certainty="0.6" xtargets="s404.1;s445.1" id="SL1019"></link>
</linkGrp>