<?xml version="1.0" encoding="utf-8"?>
<linkGrp targType="s" toDoc="en/humandocs/PDFs/EPAR/Kentera/176804en1.xml.gz" fromDoc="de/humandocs/PDFs/EPAR/Kentera/176804de1.xml.gz">
	<link certainty="2.55" xtargets="s1.1;s1.1" id="SL2"></link>
	<link certainty="0.3" xtargets="s2.1;s2.1" id="SL4"></link>
	<link certainty="1.46409" xtargets="s3.1;s3.1" id="SL6"></link>
	<link certainty="1.8" xtargets="s4.1;s4.1" id="SL8"></link>
	<link certainty="0.5375" xtargets="s5.1;s5.1" id="SL10"></link>
	<link certainty="1.140986" xtargets="s6.1;s6.1 s6.2" id="SL12"></link>
	<link certainty="1.800559" xtargets="s6.2;s6.3" id="SL13"></link>
	<link certainty="0.854907" xtargets="s6.3;s6.4" id="SL14"></link>
	<link certainty="2.30648" xtargets="s7.1;s7.1" id="SL16"></link>
	<link certainty="0.80648" xtargets="s7.2;s7.2" id="SL17"></link>
	<link certainty="2.28583" xtargets="s8.1;s8.1" id="SL19"></link>
	<link certainty="1.724365" xtargets="s8.2;s8.2" id="SL20"></link>
	<link certainty="0.643085" xtargets="s8.3;s8.3" id="SL21"></link>
	<link certainty="3.91212" xtargets="s9.1;s9.1" id="SL23"></link>
	<link certainty="3.569068" xtargets="s9.2;s9.2" id="SL24"></link>
	<link certainty="2.562338" xtargets="s9.3;s9.3" id="SL25"></link>
	<link certainty="1.73872" xtargets="s9.4;s9.4" id="SL26"></link>
	<link certainty="2.94534" xtargets="s10.1;s10.1" id="SL28"></link>
	<link certainty="2.236446" xtargets="s10.2;s10.2" id="SL29"></link>
	<link certainty="1.472295" xtargets="s10.3;s10.3" id="SL30"></link>
	<link certainty="1.49625" xtargets="s10.4;s10.4" id="SL31"></link>
	<link certainty="1.0035" xtargets="s10.5;s10.5" id="SL32"></link>
	<link certainty="0.241379" xtargets="s10.6;s10.6" id="SL33"></link>
	<link certainty="4.27964" xtargets="s11.1;s11.1" id="SL35"></link>
	<link certainty="5.28321" xtargets="s11.2;s11.2" id="SL36"></link>
	<link certainty="2.28662459" xtargets="s11.3;s11.3" id="SL37"></link>
	<link certainty="-0.00540541" xtargets="s11.4 s11.5;s11.4" id="SL38"></link>
	<link certainty="1.894322" xtargets="s11.6;s12.1 s12.2" id="SL39"></link>
	<link certainty="0.78922" xtargets="s11.7 s11.8;s12.3" id="SL40"></link>
	<link certainty="1.73267" xtargets="s11.9 s11.10;s12.4" id="SL41"></link>
	<link certainty="2.012908" xtargets="s12.1;s13.1" id="SL43"></link>
	<link certainty="1.984938" xtargets="s12.2;s13.2" id="SL44"></link>
	<link certainty="1.483301" xtargets="s12.3;s13.3" id="SL45"></link>
	<link certainty="1.492131" xtargets="s12.4;s13.4" id="SL46"></link>
	<link certainty="1.01419" xtargets="s12.5;s13.5" id="SL47"></link>
	<link certainty="2.107377" xtargets="s13.1;s14.1" id="SL49"></link>
	<link certainty="0.9242186" xtargets="s13.2;s14.2" id="SL50"></link>
	<link certainty="0.0946216" xtargets="s13.3;s14.3 s14.4" id="SL51"></link>
	<link certainty="2.435" xtargets="s14.1;s15.1" id="SL53"></link>
	<link certainty="1.175" xtargets="s14.2 s14.3;s15.2" id="SL54"></link>
	<link certainty="1.04211" xtargets="s15.1;s16.1" id="SL56"></link>
	<link certainty="0.55" xtargets="s16.1 s16.2;s17.1" id="SL58"></link>
	<link certainty="12.3" xtargets="s17.1;s18.1" id="SL60"></link>
	<link certainty="0.6" xtargets="s18.1;s19.1" id="SL62"></link>
</linkGrp><?xml version="1.0" encoding="utf-8"?>
<linkGrp targType="s" toDoc="en/humandocs/PDFs/EPAR/Kentera/176804en1.xml.gz" fromDoc="de/humandocs/PDFs/EPAR/Kentera/176804de1.xml.gz">
	<link certainty="2.55" xtargets="s1.1;s1.1" id="SL2"></link>
	<link certainty="0.3" xtargets="s2.1;s2.1" id="SL4"></link>
	<link certainty="1.46409" xtargets="s3.1;s3.1" id="SL6"></link>
	<link certainty="1.8" xtargets="s4.1;s4.1" id="SL8"></link>
	<link certainty="0.5375" xtargets="s5.1;s5.1" id="SL10"></link>
	<link certainty="1.140986" xtargets="s6.1;s6.1 s6.2" id="SL12"></link>
	<link certainty="1.800559" xtargets="s6.2;s6.3" id="SL13"></link>
	<link certainty="0.854907" xtargets="s6.3;s6.4" id="SL14"></link>
	<link certainty="2.30648" xtargets="s7.1;s7.1" id="SL16"></link>
	<link certainty="0.80648" xtargets="s7.2;s7.2" id="SL17"></link>
	<link certainty="2.28583" xtargets="s8.1;s8.1" id="SL19"></link>
	<link certainty="1.724365" xtargets="s8.2;s8.2" id="SL20"></link>
	<link certainty="0.643085" xtargets="s8.3;s8.3" id="SL21"></link>
	<link certainty="3.91212" xtargets="s9.1;s9.1" id="SL23"></link>
	<link certainty="3.569068" xtargets="s9.2;s9.2" id="SL24"></link>
	<link certainty="2.562338" xtargets="s9.3;s9.3" id="SL25"></link>
	<link certainty="1.73872" xtargets="s9.4;s9.4" id="SL26"></link>
	<link certainty="2.94534" xtargets="s10.1;s10.1" id="SL28"></link>
	<link certainty="2.236446" xtargets="s10.2;s10.2" id="SL29"></link>
	<link certainty="1.472295" xtargets="s10.3;s10.3" id="SL30"></link>
	<link certainty="1.49625" xtargets="s10.4;s10.4" id="SL31"></link>
	<link certainty="1.0035" xtargets="s10.5;s10.5" id="SL32"></link>
	<link certainty="0.241379" xtargets="s10.6;s10.6" id="SL33"></link>
	<link certainty="4.27964" xtargets="s11.1;s11.1" id="SL35"></link>
	<link certainty="5.28321" xtargets="s11.2;s11.2" id="SL36"></link>
	<link certainty="2.28662459" xtargets="s11.3;s11.3" id="SL37"></link>
	<link certainty="-0.00540541" xtargets="s11.4 s11.5;s11.4" id="SL38"></link>
	<link certainty="1.894322" xtargets="s11.6;s12.1 s12.2" id="SL39"></link>
	<link certainty="0.78922" xtargets="s11.7 s11.8;s12.3" id="SL40"></link>
	<link certainty="1.73267" xtargets="s11.9 s11.10;s12.4" id="SL41"></link>
	<link certainty="2.012908" xtargets="s12.1;s13.1" id="SL43"></link>
	<link certainty="1.984938" xtargets="s12.2;s13.2" id="SL44"></link>
	<link certainty="1.483301" xtargets="s12.3;s13.3" id="SL45"></link>
	<link certainty="1.492131" xtargets="s12.4;s13.4" id="SL46"></link>
	<link certainty="1.01419" xtargets="s12.5;s13.5" id="SL47"></link>
	<link certainty="2.107377" xtargets="s13.1;s14.1" id="SL49"></link>
	<link certainty="0.9242186" xtargets="s13.2;s14.2" id="SL50"></link>
	<link certainty="0.0946216" xtargets="s13.3;s14.3 s14.4" id="SL51"></link>
	<link certainty="2.435" xtargets="s14.1;s15.1" id="SL53"></link>
	<link certainty="1.175" xtargets="s14.2 s14.3;s15.2" id="SL54"></link>
	<link certainty="1.04211" xtargets="s15.1;s16.1" id="SL56"></link>
	<link certainty="0.55" xtargets="s16.1 s16.2;s17.1" id="SL58"></link>
	<link certainty="12.3" xtargets="s17.1;s18.1" id="SL60"></link>
	<link certainty="0.6" xtargets="s18.1;s19.1" id="SL62"></link>
</linkGrp>